Workbook

Sheet ipl_comprehensive_dataset
A1: event_name | B1: season | C1: match_number | D1: date | E1: city | F1: venue | G1: team1 | H1: team2 | I1: toss_winner | J1: toss_decision | K1: team1_runs | L1: team1_wickets | M1: team2_runs | N1: team2_wickets | O1: winner | P1: result_type | Q1: win_by_runs | R1: win_by_wickets | S1: player_of_match | T1: match_referee | U1: umpire1 | V1: umpire2 | W1: tv_umpire | X1: reserve_umpire | Y1: match_type | Z1: overs_limit | AA1: balls_per_over | AB1: gender | AC1: team_type | AD1: team1_players | AE1: team2_players
A2: Indian Premier League | B2: 2007/08 | C2: 1 | D2: 39556 | E2: Bangalore | F2: M Chinnaswamy Stadium | G2: Royal Challengers Bangalore | H2: Kolkata Knight Riders | I2: Royal Challengers Bangalore | J2: field | K2: 82 | L2: 10 | M2: 222 | N2: 3 | O2: Kolkata Knight Riders | P2: complete | Q2: 140 | R2: 0 | S2: BB McCullum | T2: J Srinath | U2: Asad Rauf | V2: RE Koertzen | W2: AM Saheba | X2: VN Kulkarni | Y2: T20 | Z2: 20 | AA2: 6 | AB2: male | AC2: club | AD2: R Dravid, W Jaffer, V Kohli, JH Kallis, CL White, MV Boucher, B Akhil, AA Noffke, P Kumar, Z Khan, SB Joshi | AE2: SC Ganguly, BB McCullum, RT Ponting, DJ Hussey, Mohammad Hafeez, LR Shukla, WP Saha, AB Agarkar, AB Dinda, M Kartik, I Sharma
A3: Indian Premier League | B3: 2007/08 | C3: 2 | D3: 39557 | E3: Chandigarh | F3: Punjab Cricket Association Stadium, Mohali | G3: Kings XI Punjab | H3: Chennai Super Kings | I3: Chennai Super Kings | J3: bat | K3: 207 | L3: 4 | M3: 240 | N3: 5 | O3: Chennai Super Kings | P3: complete | Q3: 33 | R3: 0 | S3: MEK Hussey | T3: S Venkataraghavan | U3: MR Benson | V3: SL Shastri | W3: RB Tiffin | X3: MSS Ranawat | Y3: T20 | Z3: 20 | AA3: 6 | AB3: male | AC3: club | AD3: K Goel, JR Hopes, KC Sangakkara, Yuvraj Singh, SM Katich, IK Pathan, P Dharmani, B Lee, PP Chawla, WA Mota, S Sreesanth | AE3: PA Patel, ML Hayden, MEK Hussey, MS Dhoni, SK Raina, JDP Oram, S Badrinath, Joginder Sharma, P Amarnath, MS Gony, M Muralitharan
A4: Indian Premier League | B4: 2007/08 | C4: 3 | D4: 39557 | E4: Delhi | F4: Feroz Shah Kotla | G4: Delhi Daredevils | H4: Rajasthan Royals | I4: Rajasthan Royals | J4: bat | K4: 132 | L4: 1 | M4: 129 | N4: 8 | O4: Delhi Daredevils | P4: complete | Q4: 0 | R4: 9 | S4: MF Maharoof | T4: GR Viswanath | U4: Aleem Dar | V4: GA Pratapkumar | W4: IL Howell | X4: Unknown | Y4: T20 | Z4: 20 | AA4: 6 | AB4: male | AC4: club | AD4: G Gambhir, V Sehwag, S Dhawan, MK Tiwary, KD Karthik, R Bhatia, M Manhas, DL Vettori, MF Maharoof, B Geeves, GD McGrath | AE4: T Kohli, YK Pathan, SR Watson, M Kaif, DS Lehmann, RA Jadeja, M Rawat, D Salunkhe, SK Warne, SK Trivedi, MM Patel
A5: Indian Premier League | B5: 2007/08 | C5: 4 | D5: 39558 | E5: Kolkata | F5: Eden Gardens | G5: Kolkata Knight Riders | H5: Deccan Chargers | I5: Deccan Chargers | J5: bat | K5: 112 | L5: 5 | M5: 110 | N5: 10 | O5: Kolkata Knight Riders | P5: complete | Q5: 0 | R5: 5 | S5: DJ Hussey | T5: FM Engineer | U5: BF Bowden | V5: K Hariharan | W5: Asad Rauf | X5: F Gomes | Y5: T20 | Z5: 20 | AA5: 6 | AB5: male | AC5: club | AD5: WP Saha, BB McCullum, RT Ponting, SC Ganguly, DJ Hussey, Mohammad Hafeez, LR Shukla, AB Agarkar, AB Dinda, M Kartik, I Sharma | AE5: AC Gilchrist, Y Venugopal Rao, VVS Laxman, A Symonds, RG Sharma, SB Styris, AS Yadav, SB Bangar, WPUJC Vaas, RP Singh, PP Ojha
A6: Indian Premier League | B6: 2007/08 | C6: 5 | D6: 39558 | E6: Mumbai | F6: Wankhede Stadium | G6: Mumbai Indians | H6: Royal Challengers Bangalore | I6: Mumbai Indians | J6: bat | K6: 165 | L6: 7 | M6: 166 | N6: 5 | O6: Royal Challengers Bangalore | P6: complete | Q6: 0 | R6: 5 | S6: MV Boucher | T6: J Srinath | U6: SJ Davis | V6: DJ Harper | W6: AV Jayaprakash | X6: SN Bandekar | Y6: T20 | Z6: 20 | AA6: 6 | AB6: male | AC6: club | AD6: L Ronchi, ST Jayasuriya, DJ Thornely, RV Uthappa, PR Shah, AM Nayar, SM Pollock, Harbhajan Singh, MA Khote, A Nehra, DS Kulkarni | AE6: S Chanderpaul, R Dravid, LRPL Taylor, JH Kallis, V Kohli, MV Boucher, B Akhil, P Kumar, Z Khan, SB Joshi, R Vinay Kumar
A7: Indian Premier League | B7: 2007/08 | C7: 6 | D7: 39559 | E7: Jaipur | F7: Sawai Mansingh Stadium | G7: Rajasthan Royals | H7: Kings XI Punjab | I7: Kings XI Punjab | J7: bat | K7: 168 | L7: 4 | M7: 166 | N7: 8 | O7: Rajasthan Royals | P7: complete | Q7: 0 | R7: 6 | S7: SR Watson | T7: S Venkataraghavan | U7: Aleem Dar | V7: RB Tiffin | W7: I Shivram | X7: MSS Ranawat | Y7: T20 | Z7: 20 | AA7: 6 | AB7: male | AC7: club | AD7: M Kaif, Kamran Akmal, YK Pathan, SR Watson, DS Lehmann, RA Jadeja, Pankaj Singh, D Salunkhe, SK Warne, SK Trivedi, MM Patel | AE7: K Goel, JR Hopes, KC Sangakkara, DPMD Jayawardene, Yuvraj Singh, IK Pathan, S Sohal, B Lee, PP Chawla, WA Mota, S Sreesanth
A8: Indian Premier League | B8: 2007/08 | C8: 7 | D8: 39560 | E8: Hyderabad | F8: Rajiv Gandhi International Stadium, Uppal | G8: Deccan Chargers | H8: Delhi Daredevils | I8: Deccan Chargers | J8: bat | K8: 142 | L8: 8 | M8: 143 | N8: 1 | O8: Delhi Daredevils | P8: complete | Q8: 0 | R8: 9 | S8: V Sehwag | T8: Talat Ali | U8: IL Howell | V8: AM Saheba | W8: MR Benson | X8: C Shamshuddin | Y8: T20 | Z8: 20 | AA8: 6 | AB8: male | AC8: club | AD8: AC Gilchrist, Y Venugopal Rao, VVS Laxman, A Symonds, RG Sharma, Shahid Afridi, SB Bangar, AS Yadav, WPUJC Vaas, RP Singh, PP Ojha | AE8: G Gambhir, V Sehwag, S Dhawan, Shoaib Malik, KD Karthik, MK Tiwary, R Bhatia, MF Maharoof, Mohammad Asif, VY Mahesh, GD McGrath
A9: Indian Premier League | B9: 2007/08 | C9: 8 | D9: 39561 | E9: Chennai | F9: MA Chidambaram Stadium, Chepauk | G9: Chennai Super Kings | H9: Mumbai Indians | I9: Mumbai Indians | J9: field | K9: 208 | L9: 5 | M9: 202 | N9: 7 | O9: Chennai Super Kings | P9: complete | Q9: 6 | R9: 0 | S9: ML Hayden | T9: FM Engineer | U9: DJ Harper | V9: GA Pratapkumar | W9: BF Bowden | X9: S Ravi | Y9: T20 | Z9: 20 | AA9: 6 | AB9: male | AC9: club | AD9: PA Patel, ML Hayden, MEK Hussey, SK Raina, MS Dhoni, JDP Oram, S Badrinath, Joginder Sharma, P Amarnath, MS Gony, M Muralitharan | AE9: L Ronchi, ST Jayasuriya, RV Uthappa, SM Pollock, DJ Bravo, AM Nayar, MA Khote, Harbhajan Singh, A Nehra, VS Yeligati, DS Kulkarni
A10: Indian Premier League | B10: 2007/08 | C10: 9 | D10: 39562 | E10: Hyderabad | F10: Rajiv Gandhi International Stadium, Uppal | G10: Deccan Chargers | H10: Rajasthan Royals | I10: Rajasthan Royals | J10: field | K10: 214 | L10: 5 | M10: 217 | N10: 7 | O10: Rajasthan Royals | P10: complete | Q10: 0 | R10: 3 | S10: YK Pathan | T10: S Venkataraghavan | U10: Asad Rauf | V10: MR Benson | W10: SL Shastri | X10: C Shamshuddin | Y10: T20 | Z10: 20 | AA10: 6 | AB10: male | AC10: club | AD10: AC Gilchrist, VVS Laxman, Shahid Afridi, A Symonds, RG Sharma, AS Yadav, SB Bangar, WPUJC Vaas, RP Singh, PP Ojha, D Kalyankrishna | AE10: Kamran Akmal, GC Smith, YK Pathan, SR Watson, M Kaif, RA Jadeja, SK Warne, D Salunkhe, Pankaj Singh, SK Trivedi, MM Patel
A11: Indian Premier League | B11: 2007/08 | C11: 10 | D11: 39563 | E11: Chandigarh | F11: Punjab Cricket Association Stadium, Mohali | G11: Kings XI Punjab | H11: Mumbai Indians | I11: Mumbai Indians | J11: field | K11: 182 | L11: 10 | M11: 116 | N11: 9 | O11: Kings XI Punjab | P11: complete | Q11: 66 | R11: 0 | S11: KC Sangakkara | T11: FM Engineer | U11: Aleem Dar | V11: AM Saheba | W11: RE Koertzen | X11: HS Sekhon | Y11: T20 | Z11: 20 | AA11: 6 | AB11: male | AC11: club | AD11: K Goel, IK Pathan, KC Sangakkara, Yuvraj Singh, RR Sarwan, DPMD Jayawardene, S Sohal, B Lee, PP Chawla, S Sreesanth, VRV Singh | AE11: L Ronchi, ST Jayasuriya, RV Uthappa, DJ Bravo, SS Tiwary, SM Pollock, AM Nayar, Harbhajan Singh, MA Khote, DS Kulkarni, A Nehra
A12: Indian Premier League | B12: 2007/08 | C12: 11 | D12: 39564 | E12: Chennai | F12: MA Chidambaram Stadium, Chepauk | G12: Chennai Super Kings | H12: Kolkata Knight Riders | I12: Kolkata Knight Riders | J12: bat | K12: 152 | L12: 1 | M12: 147 | N12: 9 | O12: Chennai Super Kings | P12: complete | Q12: 0 | R12: 9 | S12: JDP Oram | T12: Talat Ali | U12: BF Bowden | V12: AV Jayaprakash | W12: SJ Davis | X12: S Ravi | Y12: T20 | Z12: 20 | AA12: 6 | AB12: male | AC12: club | AD12: PA Patel, ML Hayden, MS Dhoni, MEK Hussey, S Badrinath, SK Raina, JDP Oram, Joginder Sharma, P Amarnath, MS Gony, M Muralitharan | AE12: SC Ganguly, BB McCullum, RT Ponting, WP Saha, DJ Hussey, Mohammad Hafeez, LR Shukla, AB Agarkar, M Kartik, I Sharma, AB Dinda
A13: Indian Premier League | B13: 2007/08 | C13: 12 | D13: 39564 | E13: Bangalore | F13: M Chinnaswamy Stadium | G13: Royal Challengers Bangalore | H13: Rajasthan Royals | I13: Rajasthan Royals | J13: field | K13: 135 | L13: 8 | M13: 138 | N13: 3 | O13: Rajasthan Royals | P13: complete | Q13: 0 | R13: 7 | S13: SR Watson | T13: J Srinath | U13: MR Benson | V13: IL Howell | W13: GA Pratapkumar | X13: SK Tarapore | Y13: T20 | Z13: 20 | AA13: 6 | AB13: male | AC13: club | AD13: S Chanderpaul, R Dravid, LRPL Taylor, JH Kallis, V Kohli, MV Boucher, P Kumar, SB Joshi, Z Khan, R Vinay Kumar, A Kumble | AE13: GC Smith, M Rawat, YK Pathan, SR Watson, M Kaif, RA Jadeja, D Salunkhe, SK Warne, Sohail Tanvir, SK Trivedi, MM Patel
... A56: Indian Premier League | B56: 2007/08 | C56: 56 | D56: 39596 | E56: Chandigarh | F56: Punjab Cricket Association Stadium, Mohali | G56: Kings XI Punjab | H56: Rajasthan Royals | I56: Rajasthan Royals | J56: field | K56: 221 | L56: 3 | M56: 180 | N56: 7 | O56: Kings XI Punjab | P56: complete | Q56: 41 | R56: 0 | S56: SE Marsh | T56: S Venkataraghavan | U56: SJ Davis | V56: K Hariharan | W56: DJ Harper | X56: MS Mahal | Y56: T20 | Z56: 20 | AA56: 6 | AB56: male | AC56: club | AD56: SE Marsh, JR Hopes, Yuvraj Singh, LA Pomersbach, KC Sangakkara, RR Powar, PP Chawla, IK Pathan, VRV Singh, S Sreesanth, WA Mota | AE56: M Kaif, NK Patel, Younis Khan, SR Watson, YK Pathan, Kamran Akmal, M Rawat, D Salunkhe, Pankaj Singh, SK Trivedi, MM Patel
A57: Indian Premier League | B57: 2007/08 | C57: N/A | D57: 39598 | E57: Mumbai | F57: Wankhede Stadium | G57: Delhi Daredevils | H57: Rajasthan Royals | I57: Delhi Daredevils | J57: field | K57: 87 | L57: 10 | M57: 192 | N57: 9 | O57: Rajasthan Royals | P57: complete | Q57: 105 | R57: 0 | S57: SR Watson | T57: J Srinath | U57: BF Bowden | V57: RE Koertzen | W57: BR Doctrove | X57: Unknown | Y57: T20 | Z57: 20 | AA57: 6 | AB57: male | AC57: club | AD57: G Gambhir, V Sehwag, S Dhawan, MK Tiwary, TM Dilshan, KD Karthik, MF Maharoof, A Mishra, VY Mahesh, Mohammad Asif, GD McGrath | AE57: GC Smith, SA Asnodkar, Sohail Tanvir, SR Watson, M Kaif, YK Pathan, RA Jadeja, SK Warne, M Rawat, MM Patel, SK Trivedi
A58: Indian Premier League | B58: 2007/08 | C58: N/A | D58: 39599 | E58: Mumbai | F58: Wankhede Stadium | G58: Chennai Super Kings | H58: Kings XI Punjab | I58: Kings XI Punjab | J58: bat | K58: 116 | L58: 1 | M58: 112 | N58: 8 | O58: Chennai Super Kings | P58: complete | Q58: 0 | R58: 9 | S58: M Ntini | T58: S Venkataraghavan | U58: Asad Rauf | V58: DJ Harper | W58: K Hariharan | X58: Unknown | Y58: T20 | Z58: 20 | AA58: 6 | AB58: male | AC58: club | AD58: PA Patel, S Vidyut, SK Raina, MS Dhoni, CK Kapugedera, S Badrinath, JA Morkel, MS Gony, L Balaji, M Muralitharan, M Ntini | AE58: SE Marsh, JR Hopes, KC Sangakkara, Yuvraj Singh, DPMD Jayawardene, IK Pathan, WA Mota, PP Chawla, RR Powar, S Sreesanth, VRV Singh
A59: Indian Premier League | B59: 2007/08 | C59: N/A | D59: 39600 | E59: Mumbai | F59: Dr DY Patil Sports Academy | G59: Chennai Super Kings | H59: Rajasthan Royals | I59: Rajasthan Royals | J59: field | K59: 163 | L59: 5 | M59: 164 | N59: 7 | O59: Rajasthan Royals | P59: complete | Q59: 0 | R59: 3 | S59: YK Pathan | T59: J Srinath | U59: BF Bowden | V59: RE Koertzen | W59: DJ Harper | X59: MR Singh | Y59: T20 | Z59: 20 | AA59: 6 | AB59: male | AC59: club | AD59: PA Patel, S Vidyut, SK Raina, JA Morkel, MS Dhoni, CK Kapugedera, S Badrinath, MS Gony, L Balaji, M Muralitharan, M Ntini | AE59: NK Patel, SA Asnodkar, Kamran Akmal, SR Watson, YK Pathan, M Kaif, RA Jadeja, SK Warne, Sohail Tanvir, SK Trivedi, MM Patel
A60: Indian Premier League | B60: 2009 | C60: 1 | D60: 39921 | E60: Cape Town | F60: Newlands | G60: Chennai Super Kings | H60: Mumbai Indians | I60: Chennai Super Kings | J60: field | K60: 146 | L60: 7 | M60: 165 | N60: 7 | O60: Mumbai Indians | P60: complete | Q60: 19 | R60: 0 | S60: SR Tendulkar | T60: GR Viswanath | U60: BR Doctrove | V60: K Hariharan | W60: RB Tiffin | X60: EC Hendrikse | Y60: T20 | Z60: 20 | AA60: 6 | AB60: male | AC60: club | AD60: PA Patel, ML Hayden, SK Raina, A Flintoff, MS Dhoni, JDP Oram, S Badrinath, Joginder Sharma, T Thushara, MS Gony, R Ashwin | AE60: ST Jayasuriya, SR Tendulkar, S Dhawan, JP Duminy, DJ Bravo, AM Nayar, Harbhajan Singh, Z Khan, PR Shah, SL Malinga, RR Raje
A61: Indian Premier League | B61: 2009 | C61: 2 | D61: 39921 | E61: Cape Town | F61: Newlands | G61: Royal Challengers Bangalore | H61: Rajasthan Royals | I61: Royal Challengers Bangalore | J61: bat | K61: 133 | L61: 8 | M61: 58 | N61: 10 | O61: Royal Challengers Bangalore | P61: complete | Q61: 75 | R61: 0 | S61: R Dravid | T61: GR Viswanath | U61: BR Doctrove | V61: RB Tiffin | W61: K Hariharan | X61: EC Hendrikse | Y61: T20 | Z61: 20 | AA61: 6 | AB61: male | AC61: club | AD61: JD Ryder, RV Uthappa, LRPL Taylor, KP Pietersen, R Dravid, V Kohli, B Akhil, P Kumar, R Vinay Kumar, DW Steyn, A Kumble | AE61: GC Smith, SA Asnodkar, NK Patel, T Henderson, YK Pathan, AD Mascarenhas, RA Jadeja, SK Warne, M Rawat, MM Patel, Kamran Khan
A62: Indian Premier League | B62: 2009 | C62: 3 | D62: 39922 | E62: Cape Town | F62: Newlands | G62: Delhi Daredevils | H62: Kings XI Punjab | I62: Delhi Daredevils | J62: field | K62: 58 | L62: 0 | M62: 104 | N62: 7 | O62: Delhi Daredevils | P62: complete | Q62: 0 | R62: 10 | S62: DL Vettori | T62: Yashpal Sharma | U62: MR Benson | V62: SD Ranade | W62: AL Hill | X62: MW Brown | Y62: T20 | Z62: 20 | AA62: 6 | AB62: male | AC62: club | AD62: G Gambhir, V Sehwag, TM Dilshan, AB de Villiers, MK Tiwary, KD Karthik, DP Nannes, DL Vettori, VY Mahesh, AM Salvi, PJ Sangwan | AE62: RS Bopara, K Goel, Yuvraj Singh, KC Sangakkara, DPMD Jayawardene, IK Pathan, PP Chawla, T Kohli, VS Malik, VRV Singh, YA Abdulla
A63: Indian Premier League | B63: 2009 | C63: 4 | D63: 39922 | E63: Cape Town | F63: Newlands | G63: Deccan Chargers | H63: Kolkata Knight Riders | I63: Kolkata Knight Riders | J63: bat | K63: 104 | L63: 2 | M63: 101 | N63: 10 | O63: Deccan Chargers | P63: complete | Q63: 0 | R63: 8 | S63: RP Singh | T63: Yashpal Sharma | U63: MR Benson | V63: BR Doctrove | W63: SD Ranade | X63: MW Brown | Y63: T20 | Z63: 20 | AA63: 6 | AB63: male | AC63: club | AD63: AC Gilchrist, HH Gibbs, VVS Laxman, RG Sharma, SB Styris, Y Venugopal Rao, Harmeet Singh, PP Ojha, RP Singh, DB Ravi Teja, FH Edwards | AE63: BB McCullum, CH Gayle, SC Ganguly, BJ Hodge, A Chopra, LR Shukla, MC Henriques, AB Agarkar, M Kartik, I Sharma, AB Dinda
A64: Indian Premier League | B64: 2009 | C64: 5 | D64: 39923 | E64: Port Elizabeth | F64: St George's Park | G64: Royal Challengers Bangalore | H64: Chennai Super Kings | I64: Chennai Super Kings | J64: bat | K64: 87 | L64: 10 | M64: 179 | N64: 5 | O64: Chennai Super Kings | P64: complete | Q64: 92 | R64: 0 | S64: M Muralitharan | T64: GR Viswanath | U64: BG Jerling | V64: SJA Taufel | W64: RB Tiffin | X64: S George | Y64: T20 | Z64: 20 | AA64: 6 | AB64: male | AC64: club | AD64: P Kumar, RV Uthappa, JH Kallis, LRPL Taylor, KP Pietersen, R Dravid, V Kohli, R Bishnoi, R Vinay Kumar, DW Steyn, A Kumble | AE64: PA Patel, ML Hayden, SK Raina, MS Dhoni, A Flintoff, JA Morkel, S Badrinath, Joginder Sharma, L Balaji, MS Gony, M Muralitharan
A65: Indian Premier League | B65: 2009 | C65: 6 | D65: 39924 | E65: Durban | F65: Kingsmead | G65: Kings XI Punjab | H65: Kolkata Knight Riders | I65: Kolkata Knight Riders | J65: field | K65: 158 | L65: 6 | M65: 79 | N65: 1 | O65: Kolkata Knight Riders | P65: complete | Q65: 11 | R65: 0 | S65: CH Gayle | T65: D Govindjee | U65: DJ Harper | V65: SD Ranade | W65: TH Wijewardene | X65: EC Hendrikse | Y65: T20 | Z65: 20 | AA65: 6 | AB65: male | AC65: club | AD65: RS Bopara, K Goel, IK Pathan, KC Sangakkara, Yuvraj Singh, DPMD Jayawardene, T Kohli, PP Chawla, VS Malik, VRV Singh, YA Abdulla | AE65: BB McCullum, CH Gayle, BJ Hodge, SC Ganguly, Yashpal Singh, A Chopra, MC Henriques, LR Shukla, I Sharma, M Kartik, AB Dinda
A66: Indian Premier League | B66: 2009 | C66: 8 | D66: 39925 | E66: Cape Town | F66: Newlands | G66: Royal Challengers Bangalore | H66: Deccan Chargers | I66: Deccan Chargers | J66: bat | K66: 160 | L66: 8 | M66: 184 | N66: 6 | O66: Deccan Chargers | P66: complete | Q66: 24 | R66: 0 | S66: AC Gilchrist | T66: Yashpal Sharma | U66: M Erasmus | V66: AM Saheba | W66: MR Benson | X66: Unknown | Y66: T20 | Z66: 20 | AA66: 6 | AB66: male | AC66: club | AD66: JD Ryder, RV Uthappa, JH Kallis, KP Pietersen, R Dravid, V Kohli, R Bishnoi, KV Sharma, P Kumar, A Kumble, DW Steyn | AE66: AC Gilchrist, HH Gibbs, VVS Laxman, RG Sharma, SB Styris, Y Venugopal Rao, DB Ravi Teja, FH Edwards, Harmeet Singh, PP Ojha, RP Singh
A67: Indian Premier League | B67: 2009 | C67: 9 | D67: 39926 | E67: Durban | F67: Kingsmead | G67: Chennai Super Kings | H67: Delhi Daredevils | I67: Delhi Daredevils | J67: bat | K67: 180 | L67: 9 | M67: 189 | N67: 5 | O67: Delhi Daredevils | P67: complete | Q67: 9 | R67: 0 | S67: AB de Villiers | T67: D Govindjee | U67: BR Doctrove | V67: SJA Taufel | W67: SD Ranade | X67: ZTA Ndamane | Y67: T20 | Z67: 20 | AA67: 6 | AB67: male | AC67: club | AD67: PA Patel, ML Hayden, SK Raina, MS Dhoni, A Flintoff, JA Morkel, S Badrinath, MS Gony, Joginder Sharma, L Balaji, M Muralitharan | AE67: G Gambhir, V Sehwag, AB de Villiers, TM Dilshan, KD Karthik, MK Tiwary, DL Vettori, DP Nannes, AM Salvi, PJ Sangwan, A Nehra
A68: Indian Premier League | B68: 2009 | C68: 10 | D68: 39926 | E68: Cape Town | F68: Newlands | G68: Kolkata Knight Riders | H68: Rajasthan Royals | I68: Kolkata Knight Riders | J68: field | K68: 165 | L68: 9 | M68: 168 | N68: 6 | O68: None | P68: tie | Q68: 0 | R68: 0 | S68: YK Pathan | T68: GR Viswanath | U68: MR Benson | V68: M Erasmus | W68: AM Saheba | X68: EC Hendrikse | Y68: T20 | Z68: 20 | AA68: 6 | AB68: male | AC68: club | AD68: CH Gayle, BB McCullum, LR Shukla, BJ Hodge, SC Ganguly, SB Bangar, Yashpal Singh, AB Agarkar, I Sharma, BAW Mendis, Anureet Singh | AE68: GC Smith, PC Valthaty, RJ Quiney, YK Pathan, RA Jadeja, AD Mascarenhas, AS Raut, SK Warne, M Rawat, MM Patel, Kamran Khan
A69: Indian Premier League | B69: 2009 | C69: 11 | D69: 39927 | E69: Durban | F69: Kingsmead | G69: Royal Challengers Bangalore | H69: Kings XI Punjab | I69: Royal Challengers Bangalore | J69: bat | K69: 168 | L69: 9 | M69: 173 | N69: 3 | O69: Kings XI Punjab | P69: complete | Q69: 0 | R69: 7 | S69: RS Bopara | T69: D Govindjee | U69: BR Doctrove | V69: TH Wijewardene | W69: SJA Taufel | X69: ZTA Ndamane | Y69: T20 | Z69: 20 | AA69: 6 | AB69: male | AC69: club | AD69: JD Ryder, RV Uthappa, JH Kallis, KP Pietersen, R Dravid, LRPL Taylor, V Kohli, P Kumar, R Vinay Kumar, Pankaj Singh, A Kumble | AE69: RS Bopara, K Goel, KC Sangakkara, Yuvraj Singh, DPMD Jayawardene, IK Pathan, WA Mota, PP Chawla, VRV Singh, RR Bose, YA Abdulla
A70: Indian Premier League | B70: 2009 | C70: 12 | D70: 39928 | E70: Durban | F70: Kingsmead | G70: Deccan Chargers | H70: Mumbai Indians | I70: Deccan Chargers | J70: bat | K70: 168 | L70: 9 | M70: 156 | N70: 7 | O70: Deccan Chargers | P70: complete | Q70: 12 | R70: 0 | S70: PP Ojha | T70: D Govindjee | U70: HDPK Dharmasena | V70: SJA Taufel | W70: SD Ranade | X70: ZTA Ndamane | Y70: T20 | Z70: 20 | AA70: 6 | AB70: male | AC70: club | AD70: AC Gilchrist, HH Gibbs, DR Smith, RG Sharma, VVS Laxman, Y Venugopal Rao, DB Ravi Teja, RP Singh, FH Edwards, PP Ojha, Harmeet Singh | AE70: ST Jayasuriya, SR Tendulkar, JP Duminy, S Dhawan, DJ Bravo, AM Nayar, Harbhajan Singh, Z Khan, PR Shah, SL Malinga, DS Kulkarni
A71: Indian Premier League | B71: 2009 | C71: 14 | D71: 39929 | E71: Port Elizabeth | F71: St George's Park | G71: Royal Challengers Bangalore | H71: Delhi Daredevils | I71: Royal Challengers Bangalore | J71: bat | K71: 149 | L71: 7 | M71: 150 | N71: 4 | O71: Delhi Daredevils | P71: complete | Q71: 0 | R71: 6 | S71: TM Dilshan | T71: Yashpal Sharma | U71: S Asnani | V71: BG Jerling | W71: BR Doctrove | X71: S George | Y71: T20 | Z71: 20 | AA71: 6 | AB71: male | AC71: club | AD71: JH Kallis, RV Uthappa, KP Pietersen, LRPL Taylor, V Kohli, MV Boucher, B Akhil, R Vinay Kumar, Pankaj Singh, A Kumble, KP Appanna | AE71: G Gambhir, V Sehwag, TM Dilshan, AB de Villiers, KD Karthik, M Manhas, A Mishra, DL Vettori, DP Nannes, PJ Sangwan, A Nehra
... A113: Indian Premier League | B113: 2009 | C113: 56 | D113: 39954 | E113: Centurion | F113: SuperSport Park | G113: Royal Challengers Bangalore | H113: Deccan Chargers | I113: Royal Challengers Bangalore | J113: bat | K113: 170 | L113: 4 | M113: 158 | N113: 6 | O113: Royal Challengers Bangalore | P113: complete | Q113: 12 | R113: 0 | S113: MK Pandey | T113: S Venkataraghavan | U113: IL Howell | V113: S Ravi | W113: SK Tarapore | X113: MW Brown | Y113: T20 | Z113: 20 | AA113: 6 | AB113: male | AC113: club | AD113: JH Kallis, MK Pandey, RE van der Merwe, R Dravid, LRPL Taylor, V Kohli, RV Uthappa, MV Boucher, P Kumar, B Akhil, A Kumble | AE113: AC Gilchrist, HH Gibbs, TL Suman, A Symonds, RG Sharma, Y Venugopal Rao, AA Bilakhia, RJ Harris, Jaskaran Singh, RP Singh, PP Ojha
A114: Indian Premier League | B114: 2009 | C114: N/A | D114: 39955 | E114: Centurion | F114: SuperSport Park | G114: Delhi Daredevils | H114: Deccan Chargers | I114: Deccan Chargers | J114: field | K114: 153 | L114: 8 | M114: 154 | N114: 4 | O114: Deccan Chargers | P114: complete | Q114: 0 | R114: 6 | S114: AC Gilchrist | T114: S Venkataraghavan | U114: BR Doctrove | V114: DJ Harper | W114: RE Koertzen | X114: JD Cloete | Y114: T20 | Z114: 20 | AA114: 6 | AB114: male | AC114: club | AD114: G Gambhir, DA Warner, V Sehwag, TM Dilshan, AB de Villiers, KD Karthik, R Bhatia, A Mishra, PJ Sangwan, DP Nannes, A Nehra | AE114: AC Gilchrist, HH Gibbs, AA Bilakhia, TL Suman, A Symonds, RG Sharma, Y Venugopal Rao, RJ Harris, PP Ojha, Harmeet Singh, RP Singh
A115: Indian Premier League | B115: 2009 | C115: N/A | D115: 39956 | E115: Johannesburg | F115: New Wanderers Stadium | G115: Royal Challengers Bangalore | H115: Chennai Super Kings | I115: Royal Challengers Bangalore | J115: field | K115: 149 | L115: 4 | M115: 146 | N115: 5 | O115: Royal Challengers Bangalore | P115: complete | Q115: 0 | R115: 6 | S115: MK Pandey | T115: J Srinath | U115: RE Koertzen | V115: SJA Taufel | W115: IL Howell | X115: KH Hurter | Y115: T20 | Z115: 20 | AA115: 6 | AB115: male | AC115: club | AD115: JH Kallis, MK Pandey, RE van der Merwe, R Dravid, V Kohli, LRPL Taylor, RV Uthappa, MV Boucher, P Kumar, R Vinay Kumar, A Kumble | AE115: PA Patel, ML Hayden, MS Dhoni, SK Raina, JA Morkel, JDP Oram, S Badrinath, SB Jakati, L Balaji, M Muralitharan, MS Gony
A116: Indian Premier League | B116: 2009 | C116: N/A | D116: 39957 | E116: Johannesburg | F116: New Wanderers Stadium | G116: Royal Challengers Bangalore | H116: Deccan Chargers | I116: Royal Challengers Bangalore | J116: field | K116: 137 | L116: 9 | M116: 143 | N116: 6 | O116: Deccan Chargers | P116: complete | Q116: 6 | R116: 0 | S116: A Kumble | T116: J Srinath | U116: RE Koertzen | V116: SJA Taufel | W116: DJ Harper | X116: ZTA Ndamane | Y116: T20 | Z116: 20 | AA116: 6 | AB116: male | AC116: club | AD116: JH Kallis, MK Pandey, RE van der Merwe, R Dravid, LRPL Taylor, V Kohli, MV Boucher, RV Uthappa, P Kumar, R Vinay Kumar, A Kumble | AE116: AC Gilchrist, HH Gibbs, TL Suman, A Symonds, RG Sharma, Y Venugopal Rao, AA Bilakhia, RJ Harris, PP Ojha, Harmeet Singh, RP Singh
A117: Indian Premier League | B117: 2009/10 | C117: 1 | D117: 40249 | E117: Mumbai | F117: Dr DY Patil Sports Academy | G117: Deccan Chargers | H117: Kolkata Knight Riders | I117: Deccan Chargers | J117: field | K117: 150 | L117: 7 | M117: 161 | N117: 4 | O117: Kolkata Knight Riders | P117: complete | Q117: 11 | R117: 0 | S117: AD Mathews | T117: AJ Pycroft | U117: RE Koertzen | V117: RB Tiffin | W117: BG Jerling | X117: SN Bandekar | Y117: T20 | Z117: 20 | AA117: 6 | AB117: male | AC117: club | AD117: AC Gilchrist, VVS Laxman, HH Gibbs, A Symonds, RG Sharma, Anirudh Singh, TL Suman, WPUJC Vaas, Jaskaran Singh, RP Singh, PP Ojha | AE117: MK Tiwary, BJ Hodge, SC Ganguly, CA Pujara, OA Shah, AD Mathews, WP Saha, LR Shukla, M Kartik, CK Langeveldt, I Sharma
A118: Indian Premier League | B118: 2009/10 | C118: 2 | D118: 40250 | E118: Mumbai | F118: Brabourne Stadium | G118: Mumbai Indians | H118: Rajasthan Royals | I118: Mumbai Indians | J118: bat | K118: 212 | L118: 7 | M118: 208 | N118: 7 | O118: Mumbai Indians | P118: complete | Q118: 4 | R118: 0 | S118: YK Pathan | T118: AJ Pycroft | U118: RE Koertzen | V118: RB Tiffin | W118: BG Jerling | X118: VM Bandiwadekar | Y118: T20 | Z118: 20 | AA118: 6 | AB118: male | AC118: club | AD118: ST Jayasuriya, SR Tendulkar, AP Tare, SS Tiwary, AT Rayudu, R Sathish, Harbhajan Singh, R McLaren, Z Khan, SL Malinga, AG Murtaza | AE118: GC Smith, SA Asnodkar, NV Ojha, AA Jhunjhunwala, YK Pathan, P Dogra, AD Mascarenhas, A Uniyal, SK Warne, Kamran Khan, SW Tait
A119: Indian Premier League | B119: 2009/10 | C119: 3 | D119: 40250 | E119: Chandigarh | F119: Punjab Cricket Association Stadium, Mohali | G119: Kings XI Punjab | H119: Delhi Daredevils | I119: Delhi Daredevils | J119: field | K119: 142 | L119: 9 | M119: 146 | N119: 5 | O119: Delhi Daredevils | P119: complete | Q119: 0 | R119: 5 | S119: G Gambhir | T119: S Venkataraghavan | U119: BR Doctrove | V119: S Ravi | W119: SK Tarapore | X119: C Shamshuddin | Y119: T20 | Z119: 20 | AA119: 6 | AB119: male | AC119: club | AD119: RS Bopara, MS Bisla, KC Sangakkara, Yuvraj Singh, DPMD Jayawardene, IK Pathan, M Kaif, PP Chawla, RR Powar, S Sreesanth, YA Abdulla | AE119: G Gambhir, V Sehwag, TM Dilshan, AB de Villiers, KD Karthik, M Manhas, MF Maharoof, A Mishra, PJ Sangwan, VY Mahesh, DP Nannes
A120: Indian Premier League | B120: 2009/10 | C120: 4 | D120: 40251 | E120: Kolkata | F120: Eden Gardens | G120: Kolkata Knight Riders | H120: Royal Challengers Bangalore | I120: Kolkata Knight Riders | J120: field | K120: 136 | L120: 3 | M120: 135 | N120: 7 | O120: Kolkata Knight Riders | P120: complete | Q120: 0 | R120: 7 | S120: MK Tiwary | T120: Yashpal Sharma | U120: HDPK Dharmasena | V120: AM Saheba | W120: M Erasmus | X120: R Shankar | Y120: T20 | Z120: 20 | AA120: 6 | AB120: male | AC120: club | AD120: BJ Hodge, MK Tiwary, SC Ganguly, CA Pujara, OA Shah, RS Gavaskar, AD Mathews, WP Saha, M Kartik, CK Langeveldt, I Sharma | AE120: JH Kallis, SP Goswami, MK Pandey, V Kohli, EJG Morgan, R Dravid, RV Uthappa, RE van der Merwe, P Kumar, A Kumble, DW Steyn
A121: Indian Premier League | B121: 2009/10 | C121: 5 | D121: 40251 | E121: Chennai | F121: MA Chidambaram Stadium, Chepauk | G121: Chennai Super Kings | H121: Deccan Chargers | I121: Deccan Chargers | J121: bat | K121: 159 | L121: 9 | M121: 190 | N121: 4 | O121: Deccan Chargers | P121: complete | Q121: 31 | R121: 0 | S121: WPUJC Vaas | T121: D Govindjee | U121: K Hariharan | V121: DJ Harper | W121: S Das | X121: J Madanagopal | Y121: T20 | Z121: 20 | AA121: 6 | AB121: male | AC121: club | AD121: M Vijay, ML Hayden, SK Raina, S Badrinath, JM Kemp, MS Dhoni, JA Morkel, R Ashwin, L Balaji, M Muralitharan, S Tyagi | AE121: AC Gilchrist, VVS Laxman, HH Gibbs, A Symonds, RG Sharma, TL Suman, Anirudh Singh, WPUJC Vaas, Jaskaran Singh, RP Singh, PP Ojha
A122: Indian Premier League | B122: 2009/10 | C122: 6 | D122: 40252 | E122: Ahmedabad | F122: Sardar Patel Stadium, Motera | G122: Rajasthan Royals | H122: Delhi Daredevils | I122: Delhi Daredevils | J122: field | K122: 141 | L122: 6 | M122: 142 | N122: 4 | O122: Delhi Daredevils | P122: complete | Q122: 0 | R122: 6 | S122: V Sehwag | T122: AJ Pycroft | U122: BG Jerling | V122: RE Koertzen | W122: RB Tiffin | X122: S Dua | Y122: T20 | Z122: 20 | AA122: 6 | AB122: male | AC122: club | AD122: SA Asnodkar, GC Smith, NV Ojha, YK Pathan, AA Jhunjhunwala, P Dogra, AD Mascarenhas, A Uniyal, SK Warne, SW Tait, MM Patel | AE122: G Gambhir, V Sehwag, TM Dilshan, AB de Villiers, KD Karthik, M Manhas, MF Maharoof, A Mishra, S Ladda, PJ Sangwan, DP Nannes
A123: Indian Premier League | B123: 2009/10 | C123: 7 | D123: 40253 | E123: Bangalore | F123: M Chinnaswamy Stadium | G123: Royal Challengers Bangalore | H123: Kings XI Punjab | I123: Kings XI Punjab | J123: bat | K123: 204 | L123: 2 | M123: 203 | N123: 3 | O123: Royal Challengers Bangalore | P123: complete | Q123: 0 | R123: 8 | S123: JH Kallis | T123: D Govindjee | U123: S Das | V123: DJ Harper | W123: K Hariharan | X123: KN Ananthapadmanabhan | Y123: T20 | Z123: 20 | AA123: 6 | AB123: male | AC123: club | AD123: MK Pandey, JH Kallis, RV Uthappa, V Kohli, R Dravid, EJG Morgan, MV Boucher, P Kumar, A Kumble, DW Steyn, R Vinay Kumar | AE123: RS Bopara, MS Bisla, Yuvraj Singh, DPMD Jayawardene, IK Pathan, KC Sangakkara, M Kaif, PP Chawla, Bipul Sharma, YA Abdulla, S Sreesanth
A124: Indian Premier League | B124: 2009/10 | C124: 8 | D124: 40253 | E124: Kolkata | F124: Eden Gardens | G124: Kolkata Knight Riders | H124: Chennai Super Kings | I124: Chennai Super Kings | J124: bat | K124: 109 | L124: 10 | M124: 164 | N124: 3 | O124: Chennai Super Kings | P124: complete | Q124: 55 | R124: 0 | S124: MS Dhoni | T124: Yashpal Sharma | U124: HDPK Dharmasena | V124: AM Saheba | W124: M Erasmus | X124: R Shankar | Y124: T20 | Z124: 20 | AA124: 6 | AB124: male | AC124: club | AD124: BJ Hodge, MK Tiwary, SC Ganguly, WP Saha, OA Shah, AD Mathews, LR Shukla, RS Gavaskar, SE Bond, M Kartik, I Sharma | AE124: M Vijay, ML Hayden, SK Raina, S Badrinath, MS Dhoni, JM Kemp, JA Morkel, R Ashwin, L Balaji, M Muralitharan, MS Gony
A125: Indian Premier League | B125: 2009/10 | C125: 9 | D125: 40254 | E125: Delhi | F125: Feroz Shah Kotla | G125: Delhi Daredevils | H125: Mumbai Indians | I125: Delhi Daredevils | J125: field | K125: 120 | L125: 9 | M125: 218 | N125: 7 | O125: Mumbai Indians | P125: complete | Q125: 98 | R125: 0 | S125: SR Tendulkar | T125: S Venkataraghavan | U125: BR Doctrove | V125: SK Tarapore | W125: S Ravi | X125: AK Chaudhary | Y125: T20 | Z125: 20 | AA125: 6 | AB125: male | AC125: club | AD125: TM Dilshan, V Sehwag, AB de Villiers, MF Maharoof, KD Karthik, M Manhas, A Mishra, PJ Sangwan, S Ladda, DP Nannes, G Gambhir | AE125: ST Jayasuriya, SR Tendulkar, AP Tare, SS Tiwary, AT Rayudu, KA Pollard, DJ Bravo, R Sathish, Harbhajan Singh, Z Khan, SL Malinga
A126: Indian Premier League | B126: 2009/10 | C126: 10 | D126: 40255 | E126: Bangalore | F126: M Chinnaswamy Stadium | G126: Royal Challengers Bangalore | H126: Rajasthan Royals | I126: Royal Challengers Bangalore | J126: field | K126: 93 | L126: 0 | M126: 92 | N126: 10 | O126: Royal Challengers Bangalore | P126: complete | Q126: 0 | R126: 10 | S126: JH Kallis | T126: D Govindjee | U126: K Hariharan | V126: DJ Harper | W126: S Das | X126: KN Ananthapadmanabhan | Y126: T20 | Z126: 20 | AA126: 6 | AB126: male | AC126: club | AD126: MK Pandey, JH Kallis, RV Uthappa, V Kohli, R Dravid, EJG Morgan, MV Boucher, P Kumar, A Kumble, DW Steyn, R Vinay Kumar | AE126: NV Ojha, MJ Lumb, DR Martyn, AA Jhunjhunwala, YK Pathan, P Dogra, S Narwal, SK Warne, M Morkel, MM Patel, SK Trivedi
A127: Indian Premier League | B127: 2009/10 | C127: 11 | D127: 40256 | E127: Delhi | F127: Feroz Shah Kotla | G127: Delhi Daredevils | H127: Chennai Super Kings | I127: Delhi Daredevils | J127: bat | K127: 185 | L127: 6 | M127: 190 | N127: 5 | O127: Chennai Super Kings | P127: complete | Q127: 0 | R127: 5 | S127: ML Hayden | T127: S Venkataraghavan | U127: BR Doctrove | V127: SK Tarapore | W127: S Ravi | X127: AK Chaudhary | Y127: T20 | Z127: 20 | AA127: 6 | AB127: male | AC127: club | AD127: DA Warner, V Sehwag, TM Dilshan, KD Karthik, AB de Villiers, M Manhas, R Bhatia, A Mishra, PJ Sangwan, DP Nannes, UT Yadav | AE127: PA Patel, ML Hayden, S Badrinath, SK Raina, JA Morkel, JM Kemp, M Vijay, R Ashwin, L Balaji, M Muralitharan, Joginder Sharma
A128: Indian Premier League | B128: 2009/10 | C128: 12 | D128: 40256 | E128: Cuttack | F128: Barabati Stadium | G128: Deccan Chargers | H128: Kings XI Punjab | I128: Kings XI Punjab | J128: field | K128: 170 | L128: 8 | M128: 164 | N128: 8 | O128: Deccan Chargers | P128: complete | Q128: 6 | R128: 0 | S128: A Symonds | T128: GR Viswanath | U128: BF Bowden | V128: M Erasmus | W128: AM Saheba | X128: BK Ravi | Y128: T20 | Z128: 20 | AA128: 6 | AB128: male | AC128: club | AD128: AC Gilchrist, VVS Laxman, HH Gibbs, A Symonds, RG Sharma, Anirudh Singh, TL Suman, WPUJC Vaas, Jaskaran Singh, RP Singh, PP Ojha | AE128: RS Bopara, MS Bisla, KC Sangakkara, Yuvraj Singh, DPMD Jayawardene, AB Barath, IK Pathan, PP Chawla, Bipul Sharma, S Sreesanth, SJ Srivastava
... A172: Indian Premier League | B172: 2009/10 | C172: 56 | D172: 40287 | E172: Kolkata | F172: Eden Gardens | G172: Kolkata Knight Riders | H172: Mumbai Indians | I172: Mumbai Indians | J172: bat | K172: 135 | L172: 1 | M172: 133 | N172: 8 | O172: Kolkata Knight Riders | P172: complete | Q172: 0 | R172: 9 | S172: M Kartik | T172: AJ Pycroft | U172: BG Jerling | V172: RE Koertzen | W172: RB Tiffin | X172: R Shankar | Y172: T20 | Z172: 20 | AA172: 6 | AB172: male | AC172: club | AD172: SC Ganguly, BB McCullum, DJ Hussey, MK Tiwary, AD Mathews, CA Pujara, WP Saha, JD Unadkat, M Kartik, AB Dinda, SE Bond | AE172: AP Tare, S Dhawan, SS Tiwary, JP Duminy, R Sathish, DJ Bravo, AT Rayudu, STR Binny, R McLaren, AG Murtaza, CRD Fernando
A173: Indian Premier League | B173: 2009/10 | C173: N/A | D173: 40289 | E173: Mumbai | F173: Dr DY Patil Sports Academy | G173: Royal Challengers Bangalore | H173: Mumbai Indians | I173: Mumbai Indians | J173: bat | K173: 149 | L173: 9 | M173: 184 | N173: 5 | O173: Mumbai Indians | P173: complete | Q173: 35 | R173: 0 | S173: KA Pollard | T173: J Srinath | U173: BR Doctrove | V173: RB Tiffin | W173: DJ Harper | X173: SN Bandekar | Y173: T20 | Z173: 20 | AA173: 6 | AB173: male | AC173: club | AD173: JH Kallis, R Dravid, KP Pietersen, RV Uthappa, LRPL Taylor, V Kohli, MK Pandey, P Kumar, R Vinay Kumar, DW Steyn, A Kumble | AE173: S Dhawan, SR Tendulkar, AM Nayar, AT Rayudu, JP Duminy, SS Tiwary, KA Pollard, Harbhajan Singh, Z Khan, CRD Fernando, SL Malinga
A174: Indian Premier League | B174: 2009/10 | C174: N/A | D174: 40290 | E174: Mumbai | F174: Dr DY Patil Sports Academy | G174: Chennai Super Kings | H174: Deccan Chargers | I174: Chennai Super Kings | J174: bat | K174: 142 | L174: 7 | M174: 104 | N174: 10 | O174: Chennai Super Kings | P174: complete | Q174: 38 | R174: 0 | S174: DE Bollinger | T174: J Srinath | U174: BR Doctrove | V174: RB Tiffin | W174: DJ Harper | X174: SN Bandekar | Y174: T20 | Z174: 20 | AA174: 6 | AB174: male | AC174: club | AD174: M Vijay, ML Hayden, SK Raina, S Badrinath, MS Dhoni, JA Morkel, S Anirudha, R Ashwin, SB Jakati, DE Bollinger, M Muralitharan | AE174: AC Gilchrist, HH Gibbs, TL Suman, RG Sharma, A Symonds, MD Mishra, B Sumanth, RJ Harris, Harmeet Singh, RP Singh, PP Ojha
A175: Indian Premier League | B175: 2009/10 | C175: N/A | D175: 40292 | E175: Mumbai | F175: Dr DY Patil Sports Academy | G175: Royal Challengers Bangalore | H175: Deccan Chargers | I175: Deccan Chargers | J175: bat | K175: 86 | L175: 1 | M175: 82 | N175: 10 | O175: Royal Challengers Bangalore | P175: complete | Q175: 0 | R175: 9 | S175: A Kumble | T175: S Venkataraghavan | U175: RE Koertzen | V175: SJA Taufel | W175: S Ravi | X175: SN Bandekar | Y175: T20 | Z175: 20 | AA175: 6 | AB175: male | AC175: club | AD175: JH Kallis, R Dravid, KP Pietersen, RV Uthappa, V Kohli, CL White, B Akhil, P Kumar, A Kumble, ND Doshi, DW Steyn | AE175: AC Gilchrist, MD Mishra, Anirudh Singh, RG Sharma, A Symonds, DR Smith, Y Venugopal Rao, RJ Harris, R Sharma, Harmeet Singh, PP Ojha
A176: Indian Premier League | B176: 2009/10 | C176: N/A | D176: 40293 | E176: Mumbai | F176: Dr DY Patil Sports Academy | G176: Chennai Super Kings | H176: Mumbai Indians | I176: Chennai Super Kings | J176: bat | K176: 168 | L176: 5 | M176: 146 | N176: 9 | O176: Chennai Super Kings | P176: complete | Q176: 22 | R176: 0 | S176: SK Raina | T176: S Venkataraghavan | U176: RE Koertzen | V176: SJA Taufel | W176: S Ravi | X176: SN Bandekar | Y176: T20 | Z176: 20 | AA176: 6 | AB176: male | AC176: club | AD176: M Vijay, ML Hayden, SK Raina, S Badrinath, MS Dhoni, JA Morkel, S Anirudha, R Ashwin, SB Jakati, DE Bollinger, M Muralitharan | AE176: S Dhawan, SR Tendulkar, AM Nayar, Harbhajan Singh, AT Rayudu, SS Tiwary, JP Duminy, KA Pollard, Z Khan, SL Malinga, CRD Fernando
A177: Indian Premier League | B177: 2011 | C177: 1 | D177: 40641 | E177: Chennai | F177: MA Chidambaram Stadium, Chepauk | G177: Chennai Super Kings | H177: Kolkata Knight Riders | I177: Chennai Super Kings | J177: bat | K177: 153 | L177: 4 | M177: 151 | N177: 7 | O177: Chennai Super Kings | P177: complete | Q177: 2 | R177: 0 | S177: S Anirudha | T177: J Srinath | U177: BR Doctrove | V177: PR Reiffel | W177: S Asnani | X177: K Srinath | Y177: T20 | Z177: 20 | AA177: 6 | AB177: male | AC177: club | AD177: S Anirudha, M Vijay, SK Raina, MS Dhoni, JA Morkel, SB Styris, S Badrinath, R Ashwin, SB Jakati, TG Southee, S Randiv | AE177: MS Bisla, JH Kallis, YK Pathan, MK Tiwary, EJG Morgan, G Gambhir, LR Shukla, R Bhatia, Iqbal Abdulla, L Balaji, S Ladda
A178: Indian Premier League | B178: 2011 | C178: 2 | D178: 40642 | E178: Hyderabad | F178: Rajiv Gandhi International Stadium, Uppal | G178: Deccan Chargers | H178: Rajasthan Royals | I178: Rajasthan Royals | J178: field | K178: 137 | L178: 8 | M178: 141 | N178: 2 | O178: Rajasthan Royals | P178: complete | Q178: 0 | R178: 8 | S178: SK Trivedi | T178: AJ Pycroft | U178: RE Koertzen | V178: SK Tarapore | W178: SS Hazare | X178: C Shamshuddin | Y178: T20 | Z178: 20 | AA178: 6 | AB178: male | AC178: club | AD178: S Dhawan, IR Jaggi, KC Sangakkara, B Chipli, JP Duminy, DT Christian, DB Ravi Teja, DW Steyn, A Mishra, I Sharma, PP Ojha | AE178: AG Paunikar, R Dravid, J Botha, LRPL Taylor, AS Raut, AL Menaria, A Singh, JDP Oram, SK Warne, SK Trivedi, STR Binny
A179: Indian Premier League | B179: 2011 | C179: 3 | D179: 40642 | E179: Kochi | F179: Nehru Stadium | G179: Kochi Tuskers Kerala | H179: Royal Challengers Bangalore | I179: Kochi Tuskers Kerala | J179: bat | K179: 161 | L179: 5 | M179: 162 | N179: 4 | O179: Royal Challengers Bangalore | P179: complete | Q179: 0 | R179: 6 | S179: AB de Villiers | T179: Raju Mukherjee | U179: HDPK Dharmasena | V179: K Hariharan | W179: AL Hill | X179: KN Ananthapadmanabhan | Y179: T20 | Z179: 20 | AA179: 6 | AB179: male | AC179: club | AD179: BB McCullum, VVS Laxman, DPMD Jayawardene, BJ Hodge, RA Jadeja, RV Gomez, PA Patel, M Muralitharan, R Vinay Kumar, RP Singh, S Sreesanth | AE179: MA Agarwal, TM Dilshan, V Kohli, AB de Villiers, SS Tiwary, AUK Pathan, CA Pujara, Z Khan, DL Vettori, DP Nannes, A Mithun
A180: Indian Premier League | B180: 2011 | C180: 4 | D180: 40643 | E180: Delhi | F180: Feroz Shah Kotla | G180: Delhi Daredevils | H180: Mumbai Indians | I180: Delhi Daredevils | J180: bat | K180: 95 | L180: 10 | M180: 99 | N180: 2 | O180: Mumbai Indians | P180: complete | Q180: 0 | R180: 8 | S180: SL Malinga | T180: S Venkataraghavan | U180: AM Saheba | V180: RB Tiffin | W180: SL Shastri | X180: AK Chaudhary | Y180: T20 | Z180: 20 | AA180: 6 | AB180: male | AC180: club | AD180: DA Warner, V Sehwag, UBT Chand, AJ Finch, NV Ojha, Y Venugopal Rao, IK Pathan, RE van der Merwe, M Morkel, UT Yadav, AB Dinda | AE180: DJ Jacobs, SR Tendulkar, AT Rayudu, RG Sharma, KA Pollard, JEC Franklin, R Sathish, Harbhajan Singh, AG Murtaza, MM Patel, SL Malinga
A181: Indian Premier League | B181: 2011 | C181: 5 | D181: 40643 | E181: Mumbai | F181: Dr DY Patil Sports Academy | G181: Pune Warriors | H181: Kings XI Punjab | I181: Kings XI Punjab | J181: bat | K181: 113 | L181: 3 | M181: 112 | N181: 8 | O181: Pune Warriors | P181: complete | Q181: 0 | R181: 7 | S181: SB Wagh | T181: J Srinath | U181: BR Doctrove | V181: PR Reiffel | W181: S Asnani | X181: NA Patwardhan | Y181: T20 | Z181: 20 | AA181: 6 | AB181: male | AC181: club | AD181: GC Smith, JD Ryder, M Manhas, RV Uthappa, Yuvraj Singh, MD Mishra, R Sharma, M Kartik, SB Wagh, WD Parnell, AC Thomas | AE181: AC Gilchrist, SE Marsh, PC Valthaty, KD Karthik, AM Nayar, Sunny Singh, R McLaren, PP Chawla, P Kumar, NJ Rimmington, BA Bhatt
A182: Indian Premier League | B182: 2011 | C182: 6 | D182: 40644 | E182: Kolkata | F182: Eden Gardens | G182: Kolkata Knight Riders | H182: Deccan Chargers | I182: Kolkata Knight Riders | J182: bat | K182: 163 | L182: 4 | M182: 154 | N182: 8 | O182: Kolkata Knight Riders | P182: complete | Q182: 9 | R182: 0 | S182: JH Kallis | T182: D Govindjee | U182: RE Koertzen | V182: SK Tarapore | W182: S Ravi | X182: S Das | Y182: T20 | Z182: 20 | AA182: 6 | AB182: male | AC182: club | AD182: JH Kallis, MS Bisla, G Gambhir, MK Tiwary, YK Pathan, EJG Morgan, RN ten Doeschate, Iqbal Abdulla, R Bhatia, L Balaji, JD Unadkat | AE182: S Dhawan, IR Jaggi, B Chipli, KC Sangakkara, JP Duminy, DT Christian, DB Ravi Teja, DW Steyn, A Mishra, I Sharma, PP Ojha
A183: Indian Premier League | B183: 2011 | C183: 7 | D183: 40645 | E183: Jaipur | F183: Sawai Mansingh Stadium | G183: Rajasthan Royals | H183: Delhi Daredevils | I183: Delhi Daredevils | J183: bat | K183: 152 | L183: 4 | M183: 151 | N183: 6 | O183: Rajasthan Royals | P183: complete | Q183: 0 | R183: 6 | S183: SK Warne | T183: AJ Pycroft | U183: Aleem Dar | V183: RB Tiffin | W183: SS Hazare | X183: R Subramanian | Y183: T20 | Z183: 20 | AA183: 6 | AB183: male | AC183: club | AD183: AG Paunikar, R Dravid, J Botha, AL Menaria, AM Rahane, LRPL Taylor, AS Raut, SK Warne, A Singh, SK Trivedi, SW Tait | AE183: DA Warner, V Sehwag, AJ Finch, UBT Chand, NV Ojha, Y Venugopal Rao, IK Pathan, RE van der Merwe, M Morkel, S Nadeem, AB Dinda
A184: Indian Premier League | B184: 2011 | C184: 8 | D184: 40645 | E184: Bangalore | F184: M Chinnaswamy Stadium | G184: Royal Challengers Bangalore | H184: Mumbai Indians | I184: Mumbai Indians | J184: field | K184: 140 | L184: 4 | M184: 143 | N184: 1 | O184: Mumbai Indians | P184: complete | Q184: 0 | R184: 9 | S184: SR Tendulkar | T184: Raju Mukherjee | U184: HDPK Dharmasena | V184: AL Hill | W184: K Hariharan | X184: CK Nandan | Y184: T20 | Z184: 20 | AA184: 6 | AB184: male | AC184: club | AD184: MA Agarwal, TM Dilshan, V Kohli, AB de Villiers, AUK Pathan, SS Tiwary, CA Pujara, Z Khan, DL Vettori, DP Nannes, A Mithun | AE184: DJ Jacobs, SR Tendulkar, AT Rayudu, RG Sharma, KA Pollard, JEC Franklin, R Sathish, Harbhajan Singh, AG Murtaza, MM Patel, SL Malinga
A185: Indian Premier League | B185: 2011 | C185: 9 | D185: 40646 | E185: Chandigarh | F185: Punjab Cricket Association Stadium, Mohali | G185: Kings XI Punjab | H185: Chennai Super Kings | I185: Kings XI Punjab | J185: field | K185: 193 | L185: 4 | M185: 188 | N185: 4 | O185: Kings XI Punjab | P185: complete | Q185: 0 | R185: 6 | S185: PC Valthaty | T185: S Venkataraghavan | U185: Asad Rauf | V185: SL Shastri | W185: AM Saheba | X185: K Bharatan | Y185: T20 | Z185: 20 | AA185: 6 | AB185: male | AC185: club | AD185: PC Valthaty, AC Gilchrist, SE Marsh, Sunny Singh, AM Nayar, KD Karthik, R McLaren, P Kumar, RJ Harris, PP Chawla, BA Bhatt | AE185: S Anirudha, M Vijay, SK Raina, S Badrinath, MS Dhoni, SB Styris, JA Morkel, R Ashwin, SB Jakati, TG Southee, S Randiv
A186: Indian Premier League | B186: 2011 | C186: 10 | D186: 40646 | E186: Mumbai | F186: Dr DY Patil Sports Academy | G186: Pune Warriors | H186: Kochi Tuskers Kerala | I186: Kochi Tuskers Kerala | J186: bat | K186: 151 | L186: 6 | M186: 148 | N186: 8 | O186: Pune Warriors | P186: complete | Q186: 0 | R186: 4 | S186: MD Mishra | T186: J Srinath | U186: S Asnani | V186: PR Reiffel | W186: BR Doctrove | X186: NA Patwardhan | Y186: T20 | Z186: 20 | AA186: 6 | AB186: male | AC186: club | AD186: JD Ryder, GC Smith, M Manhas, Yuvraj Singh, RV Uthappa, MD Mishra, WD Parnell, R Sharma, M Kartik, SB Wagh, AC Thomas | AE186: BB McCullum, VVS Laxman, PA Patel, DPMD Jayawardene, BJ Hodge, RA Jadeja, RV Gomez, R Vinay Kumar, S Sreesanth, RP Singh, M Muralitharan
A187: Indian Premier League | B187: 2011 | C187: 11 | D187: 40647 | E187: Hyderabad | F187: Rajiv Gandhi International Stadium, Uppal | G187: Deccan Chargers | H187: Royal Challengers Bangalore | I187: Royal Challengers Bangalore | J187: field | K187: 175 | L187: 5 | M187: 142 | N187: 9 | O187: Deccan Chargers | P187: complete | Q187: 33 | R187: 0 | S187: DW Steyn | T187: D Govindjee | U187: RE Koertzen | V187: S Ravi | W187: SK Tarapore | X187: C Shamshuddin | Y187: T20 | Z187: 20 | AA187: 6 | AB187: male | AC187: club | AD187: S Sohal, S Dhawan, KC Sangakkara, B Chipli, JP Duminy, DT Christian, DB Ravi Teja, A Mishra, DW Steyn, I Sharma, MS Gony | AE187: MA Agarwal, TM Dilshan, Z Khan, V Kohli, AB de Villiers, SS Tiwary, CA Pujara, JJ van der Wath, DL Vettori, R Ninan, S Aravind
A188: Indian Premier League | B188: 2011 | C188: 12 | D188: 40648 | E188: Jaipur | F188: Sawai Mansingh Stadium | G188: Rajasthan Royals | H188: Kolkata Knight Riders | I188: Kolkata Knight Riders | J188: field | K188: 159 | L188: 4 | M188: 160 | N188: 1 | O188: Kolkata Knight Riders | P188: complete | Q188: 0 | R188: 9 | S188: G Gambhir | T188: AJ Pycroft | U188: Aleem Dar | V188: SS Hazare | W188: RB Tiffin | X188: R Subramanian | Y188: T20 | Z188: 20 | AA188: 6 | AB188: male | AC188: club | AD188: AG Paunikar, R Dravid, AL Menaria, SR Watson, LRPL Taylor, J Botha, AS Raut, SK Warne, A Singh, SK Trivedi, ND Doshi | AE188: MS Bisla, JH Kallis, G Gambhir, MK Tiwary, YK Pathan, EJG Morgan, Shakib Al Hasan, Iqbal Abdulla, R Bhatia, B Lee, L Balaji
... A245: Indian Premier League | B245: 2011 | C245: 70 | D245: 40685 | E245: Kolkata | F245: Eden Gardens | G245: Kolkata Knight Riders | H245: Mumbai Indians | I245: Mumbai Indians | J245: field | K245: 175 | L245: 7 | M245: 178 | N245: 5 | O245: Mumbai Indians | P245: complete | Q245: 0 | R245: 5 | S245: JEC Franklin | T245: D Govindjee | U245: SK Tarapore | V245: SJA Taufel | W245: S Ravi | X245: S Das | Y245: T20 | Z245: 20 | AA245: 6 | AB245: male | AC245: club | AD245: JH Kallis, SP Goswami, G Gambhir, MK Tiwary, YK Pathan, RN ten Doeschate, R Bhatia, Shakib Al Hasan, B Lee, L Balaji, Iqbal Abdulla | AE245: TL Suman, SR Tendulkar, Harbhajan Singh, RG Sharma, KA Pollard, JEC Franklin, AT Rayudu, R Sathish, AN Ahmed, RW Price, SL Malinga
A246: Indian Premier League | B246: 2011 | C246: N/A | D246: 40687 | E246: Mumbai | F246: Wankhede Stadium | G246: Royal Challengers Bangalore | H246: Chennai Super Kings | I246: Chennai Super Kings | J246: field | K246: 175 | L246: 4 | M246: 177 | N246: 4 | O246: Chennai Super Kings | P246: complete | Q246: 0 | R246: 6 | S246: SK Raina | T246: RS Mahanama | U246: Asad Rauf | V246: SJA Taufel | W246: PR Reiffel | X246: VA Kulkarni | Y246: T20 | Z246: 20 | AA246: 6 | AB246: male | AC246: club | AD246: MA Agarwal, CH Gayle, V Kohli, AB de Villiers, LA Pomersbach, SS Tiwary, M Kaif, DL Vettori, S Aravind, A Mithun, Z Khan | AE246: MEK Hussey, M Vijay, SK Raina, S Badrinath, MS Dhoni, JA Morkel, DJ Bravo, WP Saha, R Ashwin, DE Bollinger, SB Jakati
A247: Indian Premier League | B247: 2011 | C247: N/A | D247: 40688 | E247: Mumbai | F247: Wankhede Stadium | G247: Mumbai Indians | H247: Kolkata Knight Riders | I247: Mumbai Indians | J247: field | K247: 148 | L247: 6 | M247: 147 | N247: 7 | O247: Mumbai Indians | P247: complete | Q247: 0 | R247: 4 | S247: MM Patel | T247: RS Mahanama | U247: Asad Rauf | V247: SJA Taufel | W247: PR Reiffel | X247: VN Kulkarni | Y247: T20 | Z247: 20 | AA247: 6 | AB247: male | AC247: club | AD247: AC Blizzard, SR Tendulkar, RG Sharma, AT Rayudu, JEC Franklin, KA Pollard, TL Suman, Harbhajan Singh, DS Kulkarni, MM Patel, SL Malinga | AE247: G Gambhir, JH Kallis, SP Goswami, MK Tiwary, YK Pathan, RN ten Doeschate, Shakib Al Hasan, R Bhatia, B Lee, L Balaji, Iqbal Abdulla
A248: Indian Premier League | B248: 2011 | C248: N/A | D248: 40690 | E248: Chennai | F248: MA Chidambaram Stadium, Chepauk | G248: Royal Challengers Bangalore | H248: Mumbai Indians | I248: Mumbai Indians | J248: field | K248: 185 | L248: 4 | M248: 142 | N248: 8 | O248: Royal Challengers Bangalore | P248: complete | Q248: 43 | R248: 0 | S248: CH Gayle | T248: RS Mahanama | U248: Asad Rauf | V248: SJA Taufel | W248: HDPK Dharmasena | X248: K Srinath | Y248: T20 | Z248: 20 | AA248: 6 | AB248: male | AC248: club | AD248: MA Agarwal, CH Gayle, V Kohli, AB de Villiers, LA Pomersbach, SS Tiwary, DL Vettori, S Aravind, A Mithun, Z Khan, J Syed Mohammad | AE248: AC Blizzard, SR Tendulkar, Harbhajan Singh, RG Sharma, JEC Franklin, AT Rayudu, KA Pollard, R Sathish, SL Malinga, AN Ahmed, MM Patel
A249: Indian Premier League | B249: 2011 | C249: N/A | D249: 40691 | E249: Chennai | F249: MA Chidambaram Stadium, Chepauk | G249: Chennai Super Kings | H249: Royal Challengers Bangalore | I249: Chennai Super Kings | J249: bat | K249: 205 | L249: 5 | M249: 147 | N249: 8 | O249: Chennai Super Kings | P249: complete | Q249: 58 | R249: 0 | S249: M Vijay | T249: RS Mahanama | U249: Asad Rauf | V249: SJA Taufel | W249: HDPK Dharmasena | X249: K Srinath | Y249: T20 | Z249: 20 | AA249: 6 | AB249: male | AC249: club | AD249: MEK Hussey, M Vijay, MS Dhoni, SK Raina, JA Morkel, S Badrinath, DJ Bravo, WP Saha, R Ashwin, DE Bollinger, SB Jakati | AE249: MA Agarwal, CH Gayle, V Kohli, AB de Villiers, LA Pomersbach, SS Tiwary, DL Vettori, A Mithun, Z Khan, J Syed Mohammad, S Aravind
A250: Indian Premier League | B250: 2012 | C250: 1 | D250: 41003 | E250: Chennai | F250: MA Chidambaram Stadium, Chepauk | G250: Chennai Super Kings | H250: Mumbai Indians | I250: Mumbai Indians | J250: field | K250: 112 | L250: 10 | M250: 115 | N250: 3 | O250: Mumbai Indians | P250: complete | Q250: 0 | R250: 8 | S250: RE Levi | T250: RS Madugalle | U250: JD Cloete | V250: SJA Taufel | W250: S Ravi | X250: K Srinath | Y250: T20 | Z250: 20 | AA250: 6 | AB250: male | AC250: club | AD250: F du Plessis, M Vijay, SK Raina, DJ Bravo, JA Morkel, S Badrinath, MS Dhoni, RA Jadeja, R Ashwin, SB Jakati, DE Bollinger | AE250: RE Levi, SR Tendulkar, RG Sharma, AT Rayudu, JEC Franklin, KD Karthik, KA Pollard, Harbhajan Singh, SL Malinga, AN Ahmed, PP Ojha
A251: Indian Premier League | B251: 2012 | C251: 2 | D251: 41004 | E251: Kolkata | F251: Eden Gardens | G251: Kolkata Knight Riders | H251: Delhi Daredevils | I251: Delhi Daredevils | J251: field | K251: 97 | L251: 9 | M251: 100 | N251: 2 | O251: Delhi Daredevils | P251: complete | Q251: 0 | R251: 8 | S251: IK Pathan | T251: GF Labrooy | U251: S Asnani | V251: HDPK Dharmasena | W251: S Das | X251: Premdip Chatterjee | Y251: T20 | Z251: 20 | AA251: 6 | AB251: male | AC251: club | AD251: BB McCullum, JH Kallis, G Gambhir, MK Tiwary, YK Pathan, DB Das, LR Shukla, R Bhatia, B Lee, Iqbal Abdulla, M de Lange | AE251: AJ Finch, V Sehwag, IK Pathan, GJ Maxwell, NV Ojha, Y Venugopal Rao, M Morkel, Y Nagar, RE van der Merwe, UT Yadav, S Nadeem
A252: Indian Premier League | B252: 2012 | C252: 3 | D252: 41005 | E252: Mumbai | F252: Wankhede Stadium | G252: Mumbai Indians | H252: Pune Warriors | I252: Mumbai Indians | J252: field | K252: 101 | L252: 9 | M252: 129 | N252: 9 | O252: Pune Warriors | P252: complete | Q252: 28 | R252: 0 | S252: SPD Smith | T252: RR Jadeja | U252: AK Chaudhary | V252: SJA Taufel | W252: JD Cloete | X252: PG Pathak | Y252: T20 | Z252: 20 | AA252: 6 | AB252: male | AC252: club | AD252: RE Levi, AT Rayudu, RG Sharma, JEC Franklin, KD Karthik, SA Yadav, KA Pollard, Harbhajan Singh, SL Malinga, PP Ojha, MM Patel | AE252: MK Pandey, SC Ganguly, WD Parnell, RV Uthappa, CJ Ferguson, SPD Smith, MN Samuels, B Kumar, M Kartik, R Sharma, AB Dinda
A253: Indian Premier League | B253: 2012 | C253: 4 | D253: 41005 | E253: Jaipur | F253: Sawai Mansingh Stadium | G253: Rajasthan Royals | H253: Kings XI Punjab | I253: Kings XI Punjab | J253: field | K253: 191 | L253: 4 | M253: 160 | N253: 9 | O253: Rajasthan Royals | P253: complete | Q253: 31 | R253: 0 | S253: AM Rahane | T253: RS Madugalle | U253: BF Bowden | V253: SK Tarapore | W253: VA Kulkarni | X253: PK Khakhar | Y253: T20 | Z253: 20 | AA253: 6 | AB253: male | AC253: club | AD253: R Dravid, AM Rahane, AL Menaria, BJ Hodge, OA Shah, KK Cooper, J Botha, AA Chavan, SP Goswami, A Singh, SK Trivedi | AE253: AC Gilchrist, PC Valthaty, SE Marsh, AM Nayar, DJ Hussey, Mandeep Singh, Bipul Sharma, PP Chawla, JP Faulkner, P Kumar, Harmeet Singh
A254: Indian Premier League | B254: 2012 | C254: 5 | D254: 41006 | E254: Bangalore | F254: M Chinnaswamy Stadium | G254: Royal Challengers Bangalore | H254: Delhi Daredevils | I254: Delhi Daredevils | J254: field | K254: 157 | L254: 8 | M254: 137 | N254: 7 | O254: Royal Challengers Bangalore | P254: complete | Q254: 20 | R254: 0 | S254: AB de Villiers | T254: Raju Mukherjee | U254: S Asnani | V254: S Ravi | W254: S Das | X254: BK Ravi | Y254: T20 | Z254: 20 | AA254: 6 | AB254: male | AC254: club | AD254: AB McDonald, CA Pujara, V Kohli, AB de Villiers, SS Tiwary, MA Agarwal, DL Vettori, R Vinay Kumar, HV Patel, Z Khan, M Muralitharan | AE254: AJ Finch, V Sehwag, NV Ojha, Y Venugopal Rao, GJ Maxwell, Y Nagar, IK Pathan, DAJ Bracewell, M Morkel, UT Yadav, S Nadeem
A255: Indian Premier League | B255: 2012 | C255: 6 | D255: 41006 | E255: Visakhapatnam | F255: Dr. Y.S. Rajasekhara Reddy ACA-VDCA Cricket Stadium | G255: Deccan Chargers | H255: Chennai Super Kings | I255: Deccan Chargers | J255: field | K255: 119 | L255: 10 | M255: 193 | N255: 6 | O255: Chennai Super Kings | P255: complete | Q255: 74 | R255: 0 | S255: RA Jadeja | T255: GF Labrooy | U255: JD Cloete | V255: HDPK Dharmasena | W255: AK Chaudhary | X255: R Subramanian | Y255: T20 | Z255: 20 | AA255: 6 | AB255: male | AC255: club | AD255: DJ Harris, S Dhawan, PA Patel, CL White, B Chipli, DT Christian, MS Gony, DB Ravi Teja, Ankit Sharma, DW Steyn, TP Sudhindra | AE255: M Vijay, F du Plessis, SK Raina, S Badrinath, RA Jadeja, MS Dhoni, DJ Bravo, JA Morkel, R Ashwin, SB Jakati, DE Bollinger
A256: Indian Premier League | B256: 2012 | C256: 7 | D256: 41007 | E256: Jaipur | F256: Sawai Mansingh Stadium | G256: Rajasthan Royals | H256: Kolkata Knight Riders | I256: Kolkata Knight Riders | J256: field | K256: 164 | L256: 5 | M256: 142 | N256: 10 | O256: Rajasthan Royals | P256: complete | Q256: 22 | R256: 0 | S256: BJ Hodge | T256: RS Madugalle | U256: BF Bowden | V256: VA Kulkarni | W256: SK Tarapore | X256: PK Khakhar | Y256: T20 | Z256: 20 | AA256: 6 | AB256: male | AC256: club | AD256: R Dravid, AM Rahane, SP Goswami, AL Menaria, BJ Hodge, OA Shah, KK Cooper, J Botha, AA Chavan, A Singh, SK Trivedi | AE256: JH Kallis, BB McCullum, G Gambhir, MK Tiwary, DB Das, YK Pathan, R Bhatia, LR Shukla, B Lee, SP Narine, Iqbal Abdulla
A257: Indian Premier League | B257: 2012 | C257: 8 | D257: 41007 | E257: Pune | F257: Subrata Roy Sahara Stadium | G257: Pune Warriors | H257: Kings XI Punjab | I257: Pune Warriors | J257: bat | K257: 166 | L257: 6 | M257: 144 | N257: 8 | O257: Pune Warriors | P257: complete | Q257: 22 | R257: 0 | S257: MN Samuels | T257: RR Jadeja | U257: S Das | V257: SJA Taufel | W257: S Asnani | X257: SD Ranade | Y257: T20 | Z257: 20 | AA257: 6 | AB257: male | AC257: club | AD257: JD Ryder, SC Ganguly, MN Samuels, RV Uthappa, CJ Ferguson, SPD Smith, MK Pandey, R Sharma, M Kartik, AB Dinda, A Nehra | AE257: AC Gilchrist, PC Valthaty, Mandeep Singh, AM Nayar, DJ Hussey, PP Chawla, AD Mascarenhas, Bipul Sharma, JP Faulkner, P Kumar, Harmeet Singh
A258: Indian Premier League | B258: 2012 | C258: 9 | D258: 41008 | E258: Visakhapatnam | F258: Dr. Y.S. Rajasekhara Reddy ACA-VDCA Cricket Stadium | G258: Deccan Chargers | H258: Mumbai Indians | I258: Deccan Chargers | J258: bat | K258: 138 | L258: 9 | M258: 142 | N258: 5 | O258: Mumbai Indians | P258: complete | Q258: 0 | R258: 5 | S258: RG Sharma | T258: GF Labrooy | U258: AK Chaudhary | V258: JD Cloete | W258: HDPK Dharmasena | X258: R Subramanian | Y258: T20 | Z258: 20 | AA258: 6 | AB258: male | AC258: club | AD258: PA Patel, S Dhawan, B Chipli, DT Christian, KC Sangakkara, CL White, DB Ravi Teja, A Mishra, DW Steyn, Ankit Sharma, Anand Rajan | AE258: TL Suman, RE Levi, RG Sharma, AT Rayudu, KA Pollard, KD Karthik, JEC Franklin, Harbhajan Singh, SL Malinga, PP Ojha, MM Patel
A259: Indian Premier League | B259: 2012 | C259: 10 | D259: 41009 | E259: Bangalore | F259: M Chinnaswamy Stadium | G259: Royal Challengers Bangalore | H259: Kolkata Knight Riders | I259: Royal Challengers Bangalore | J259: field | K259: 123 | L259: 9 | M259: 165 | N259: 8 | O259: Kolkata Knight Riders | P259: complete | Q259: 42 | R259: 0 | S259: L Balaji | T259: Raju Mukherjee | U259: S Ravi | V259: RJ Tucker | W259: S Asnani | X259: BK Ravi | Y259: T20 | Z259: 20 | AA259: 6 | AB259: male | AC259: club | AD259: CA Pujara, CH Gayle, V Kohli, AB de Villiers, SS Tiwary, MA Agarwal, DL Vettori, R Vinay Kumar, HV Patel, Z Khan, M Muralitharan | AE259: JH Kallis, G Gambhir, MS Bisla, YK Pathan, MK Tiwary, RN ten Doeschate, Shakib Al Hasan, LR Shukla, B Lee, R Bhatia, L Balaji
A260: Indian Premier League | B260: 2012 | C260: 11 | D260: 41009 | E260: Delhi | F260: Feroz Shah Kotla | G260: Delhi Daredevils | H260: Chennai Super Kings | I260: Delhi Daredevils | J260: field | K260: 111 | L260: 2 | M260: 110 | N260: 8 | O260: Delhi Daredevils | P260: complete | Q260: 0 | R260: 8 | S260: M Morkel | T260: RS Madugalle | U260: Asad Rauf | V260: SK Tarapore | W260: VA Kulkarni | X260: S Dua | Y260: T20 | Z260: 20 | AA260: 6 | AB260: male | AC260: club | AD260: NV Ojha, V Sehwag, KP Pietersen, DPMD Jayawardene, RE van der Merwe, Y Venugopal Rao, Y Nagar, IK Pathan, M Morkel, UT Yadav, S Nadeem | AE260: F du Plessis, M Vijay, SK Raina, S Badrinath, RA Jadeja, DJ Bravo, MS Dhoni, JA Morkel, R Ashwin, SB Jakati, DE Bollinger
A261: Indian Premier League | B261: 2012 | C261: 12 | D261: 41010 | E261: Mumbai | F261: Wankhede Stadium | G261: Mumbai Indians | H261: Rajasthan Royals | I261: Rajasthan Royals | J261: field | K261: 197 | L261: 6 | M261: 170 | N261: 10 | O261: Mumbai Indians | P261: complete | Q261: 27 | R261: 0 | S261: KA Pollard | T261: J Srinath | U261: Aleem Dar | V261: BNJ Oxenford | W261: S Das | X261: PG Pathak | Y261: T20 | Z261: 20 | AA261: 6 | AB261: male | AC261: club | AD261: RE Levi, TL Suman, RG Sharma, AT Rayudu, KA Pollard, KD Karthik, JEC Franklin, Harbhajan Singh, SL Malinga, PP Ojha, MM Patel | AE261: R Dravid, AM Rahane, SP Goswami, OA Shah, AL Menaria, J Botha, KK Cooper, AA Chavan, GB Hogg, A Singh, SK Trivedi
... A319: Indian Premier League | B319: 2012 | C319: 72 | D319: 41049 | E319: Jaipur | F319: Sawai Mansingh Stadium | G319: Rajasthan Royals | H319: Mumbai Indians | I319: Rajasthan Royals | J319: bat | K319: 162 | L319: 6 | M319: 163 | N319: 0 | O319: Mumbai Indians | P319: complete | Q319: 0 | R319: 10 | S319: DR Smith | T319: Raju Mukherjee | U319: HDPK Dharmasena | V319: C Shamshuddin | W319: BNJ Oxenford | X319: K Bharatan | Y319: T20 | Z319: 20 | AA319: 6 | AB319: male | AC319: club | AD319: R Dravid, AM Rahane, SR Watson, STR Binny, OA Shah, AL Menaria, DH Yagnik, GB Hogg, SW Tait, SK Trivedi, A Chandila | AE319: SR Tendulkar, DR Smith, RG Sharma, KD Karthik, JEC Franklin, AT Rayudu, KA Pollard, Harbhajan Singh, SL Malinga, RP Singh, DS Kulkarni
A320: Indian Premier League | B320: 2012 | C320: N/A | D320: 41051 | E320: Pune | F320: Subrata Roy Sahara Stadium | G320: Delhi Daredevils | H320: Kolkata Knight Riders | I320: Kolkata Knight Riders | J320: bat | K320: 144 | L320: 8 | M320: 162 | N320: 4 | O320: Kolkata Knight Riders | P320: complete | Q320: 18 | R320: 0 | S320: YK Pathan | T320: AJ Pycroft | U320: BR Doctrove | V320: SJA Taufel | W320: HDPK Dharmasena | X320: NA Patwardhan | Y320: T20 | Z320: 20 | AA320: 6 | AB320: male | AC320: club | AD320: DA Warner, V Sehwag, NV Ojha, DPMD Jayawardene, Y Venugopal Rao, P Negi, LRPL Taylor, IK Pathan, M Morkel, UT Yadav, VR Aaron | AE320: BB McCullum, G Gambhir, JH Kallis, Shakib Al Hasan, YK Pathan, LR Shukla, DB Das, R Bhatia, Iqbal Abdulla, SP Narine, L Balaji
A321: Indian Premier League | B321: 2012 | C321: N/A | D321: 41052 | E321: Bangalore | F321: M Chinnaswamy Stadium | G321: Chennai Super Kings | H321: Mumbai Indians | I321: Mumbai Indians | J321: field | K321: 187 | L321: 5 | M321: 149 | N321: 9 | O321: Chennai Super Kings | P321: complete | Q321: 38 | R321: 0 | S321: MS Dhoni | T321: RS Madugalle | U321: BF Bowden | V321: HDPK Dharmasena | W321: SJA Taufel | X321: CK Nandan | Y321: T20 | Z321: 20 | AA321: 6 | AB321: male | AC321: club | AD321: M Vijay, MEK Hussey, SK Raina, S Badrinath, MS Dhoni, RA Jadeja, DJ Bravo, JA Morkel, R Ashwin, BW Hilfenhaus, SB Jakati | AE321: SR Tendulkar, DR Smith, RG Sharma, KD Karthik, JEC Franklin, AT Rayudu, KA Pollard, Harbhajan Singh, SL Malinga, DS Kulkarni, RP Singh
A322: Indian Premier League | B322: 2012 | C322: N/A | D322: 41054 | E322: Chennai | F322: MA Chidambaram Stadium, Chepauk | G322: Delhi Daredevils | H322: Chennai Super Kings | I322: Delhi Daredevils | J322: field | K322: 136 | L322: 10 | M322: 222 | N322: 5 | O322: Chennai Super Kings | P322: complete | Q322: 86 | R322: 0 | S322: M Vijay | T322: RS Madugalle | U322: BR Doctrove | V322: SJA Taufel | W322: BF Bowden | X322: K Srinath | Y322: T20 | Z322: 20 | AA322: 6 | AB322: male | AC322: club | AD322: DPMD Jayawardene, DA Warner, V Sehwag, LRPL Taylor, AD Russell, NV Ojha, Y Venugopal Rao, P Negi, Sunny Gupta, UT Yadav, VR Aaron | AE322: M Vijay, MEK Hussey, SK Raina, MS Dhoni, JA Morkel, DJ Bravo, RA Jadeja, R Ashwin, BW Hilfenhaus, SB Jakati, S Badrinath
A323: Indian Premier League | B323: 2012 | C323: N/A | D323: 41056 | E323: Chennai | F323: MA Chidambaram Stadium, Chepauk | G323: Kolkata Knight Riders | H323: Chennai Super Kings | I323: Chennai Super Kings | J323: bat | K323: 192 | L323: 5 | M323: 190 | N323: 3 | O323: Kolkata Knight Riders | P323: complete | Q323: 0 | R323: 5 | S323: MS Bisla | T323: RS Madugalle | U323: BF Bowden | V323: SJA Taufel | W323: BR Doctrove | X323: K Srinivasan | Y323: T20 | Z323: 20 | AA323: 6 | AB323: male | AC323: club | AD323: MS Bisla, G Gambhir, JH Kallis, LR Shukla, YK Pathan, Shakib Al Hasan, MK Tiwary, R Bhatia, Iqbal Abdulla, SP Narine, B Lee | AE323: MEK Hussey, M Vijay, SK Raina, MS Dhoni, DJ Bravo, RA Jadeja, JA Morkel, R Ashwin, BW Hilfenhaus, SB Jakati, S Badrinath
A324: Indian Premier League | B324: 2013 | C324: 1 | D324: 41367 | E324: Kolkata | F324: Eden Gardens | G324: Kolkata Knight Riders | H324: Delhi Daredevils | I324: Kolkata Knight Riders | J324: field | K324: 129 | L324: 4 | M324: 128 | N324: 10 | O324: Kolkata Knight Riders | P324: complete | Q324: 0 | R324: 6 | S324: SP Narine | T324: DC Boon | U324: S Ravi | V324: SJA Taufel | W324: S Asnani | X324: AS Pathania | Y324: T20 | Z324: 20 | AA324: 6 | AB324: male | AC324: club | AD324: MS Bisla, G Gambhir, JH Kallis, MK Tiwary, EJG Morgan, YK Pathan, LR Shukla, R Bhatia, B Lee, SP Narine, L Balaji | AE324: UBT Chand, DA Warner, DPMD Jayawardene, MC Juneja, NV Ojha, J Botha, IK Pathan, AD Russell, S Nadeem, A Nehra, UT Yadav
A325: Indian Premier League | B325: 2013 | C325: 2 | D325: 41368 | E325: Bangalore | F325: M Chinnaswamy Stadium | G325: Royal Challengers Bangalore | H325: Mumbai Indians | I325: Mumbai Indians | J325: field | K325: 156 | L325: 5 | M325: 154 | N325: 5 | O325: Royal Challengers Bangalore | P325: complete | Q325: 2 | R325: 0 | S325: CH Gayle | T325: AJ Pycroft | U325: VA Kulkarni | V325: C Shamshuddin | W325: K Srinath | X325: KN Ananthapadmanabhan | Y325: T20 | Z325: 20 | AA325: 6 | AB325: male | AC325: club | AD325: CH Gayle, TM Dilshan, V Kohli, MA Agarwal, DT Christian, KK Nair, KB Arun Karthik, R Vinay Kumar, M Kartik, JD Unadkat, M Muralitharan | AE325: RT Ponting, SR Tendulkar, KD Karthik, RG Sharma, AT Rayudu, KA Pollard, Harbhajan Singh, JJ Bumrah, MG Johnson, JDP Oram, MM Patel
A326: Indian Premier League | B326: 2013 | C326: 3 | D326: 41369 | E326: Hyderabad | F326: Rajiv Gandhi International Stadium, Uppal | G326: Sunrisers Hyderabad | H326: Pune Warriors | I326: Pune Warriors | J326: field | K326: 126 | L326: 6 | M326: 104 | N326: 10 | O326: Sunrisers Hyderabad | P326: complete | Q326: 22 | R326: 0 | S326: A Mishra | T326: DC Boon | U326: S Ravi | V326: SJA Taufel | W326: CK Nandan | X326: A Nand Kishore | Y326: T20 | Z326: 20 | AA326: 6 | AB326: male | AC326: club | AD326: PA Reddy, PA Patel, KC Sangakkara, CL White, NLTC Perera, GH Vihari, A Ashish Reddy, DB Ravi Teja, A Mishra, DW Steyn, I Sharma | AE326: RV Uthappa, MK Pandey, MN Samuels, Yuvraj Singh, LRPL Taylor, AM Nayar, AD Mathews, MR Marsh, B Kumar, R Sharma, AB Dinda
A327: Indian Premier League | B327: 2013 | C327: 4 | D327: 41370 | E327: Delhi | F327: Feroz Shah Kotla | G327: Delhi Daredevils | H327: Rajasthan Royals | I327: Rajasthan Royals | J327: bat | K327: 160 | L327: 6 | M327: 165 | N327: 7 | O327: Rajasthan Royals | P327: complete | Q327: 5 | R327: 0 | S327: R Dravid | T327: AJ Pycroft | U327: S Das | V327: C Shamshuddin | W327: AK Chaudhary | X327: K Bharatan | Y327: T20 | Z327: 20 | AA327: 6 | AB327: male | AC327: club | AD327: DA Warner, UBT Chand, DPMD Jayawardene, MC Juneja, AD Russell, J Botha, IK Pathan, NV Ojha, A Nehra, S Nadeem, UT Yadav | AE327: MDKJ Perera, AM Rahane, R Dravid, STR Binny, BJ Hodge, KK Cooper, AL Menaria, S Sreesanth, R Shukla, SK Trivedi, S Badree
A328: Indian Premier League | B328: 2013 | C328: 5 | D328: 41370 | E328: Chennai | F328: MA Chidambaram Stadium, Chepauk | G328: Chennai Super Kings | H328: Mumbai Indians | I328: Mumbai Indians | J328: bat | K328: 139 | L328: 9 | M328: 148 | N328: 6 | O328: Mumbai Indians | P328: complete | Q328: 9 | R328: 0 | S328: KA Pollard | T328: J Srinath | U328: M Erasmus | V328: VA Kulkarni | W328: K Srinath | X328: K Srinivasan | Y328: T20 | Z328: 20 | AA328: 6 | AB328: male | AC328: club | AD328: MEK Hussey, M Vijay, SK Raina, DJ Bravo, S Badrinath, MS Dhoni, RA Jadeja, R Ashwin, B Laughlin, AS Rajpoot, DP Nannes | AE328: RT Ponting, SR Tendulkar, KD Karthik, RG Sharma, AT Rayudu, KA Pollard, DR Smith, Harbhajan Singh, MG Johnson, MM Patel, PP Ojha
A329: Indian Premier League | B329: 2013 | C329: 6 | D329: 41371 | E329: Pune | F329: Subrata Roy Sahara Stadium | G329: Pune Warriors | H329: Kings XI Punjab | I329: Pune Warriors | J329: bat | K329: 99 | L329: 9 | M329: 100 | N329: 2 | O329: Kings XI Punjab | P329: complete | Q329: 0 | R329: 8 | S329: M Vohra | T329: RS Madugalle | U329: S Asnani | V329: SJA Taufel | W329: CK Nandan | X329: PG Pathak | Y329: T20 | Z329: 20 | AA329: 6 | AB329: male | AC329: club | AD329: RV Uthappa, MK Pandey, TL Suman, MN Samuels, LRPL Taylor, AD Mathews, AM Nayar, MR Marsh, B Kumar, R Sharma, AB Dinda | AE329: AC Gilchrist, Mandeep Singh, M Vohra, DJ Hussey, Azhar Mahmood, Gurkeerat Singh, R Sathish, PP Chawla, P Awana, P Kumar, RJ Harris
A330: Indian Premier League | B330: 2013 | C330: 7 | D330: 41371 | E330: Hyderabad | F330: Rajiv Gandhi International Stadium, Uppal | G330: Sunrisers Hyderabad | H330: Royal Challengers Bangalore | I330: Royal Challengers Bangalore | J330: bat | K330: 150 | L330: 7 | M330: 145 | N330: 8 | O330: None | P330: tie | Q330: 0 | R330: 0 | S330: GH Vihari | T330: DC Boon | U330: AK Chaudhary | V330: S Ravi | W330: K Srinath | X330: A Nand Kishore | Y330: T20 | Z330: 20 | AA330: 6 | AB330: male | AC330: club | AD330: PA Reddy, PA Patel, CL White, GH Vihari, KC Sangakkara, NLTC Perera, A Mishra, A Ashish Reddy, DW Steyn, Ankit Sharma, I Sharma | AE330: CH Gayle, TM Dilshan, V Kohli, KK Nair, MC Henriques, MA Agarwal, KB Arun Karthik, R Vinay Kumar, M Kartik, JD Unadkat, M Muralitharan
A331: Indian Premier League | B331: 2013 | C331: 8 | D331: 41372 | E331: Jaipur | F331: Sawai Mansingh Stadium | G331: Rajasthan Royals | H331: Kolkata Knight Riders | I331: Kolkata Knight Riders | J331: field | K331: 144 | L331: 6 | M331: 125 | N331: 10 | O331: Rajasthan Royals | P331: complete | Q331: 19 | R331: 0 | S331: SK Trivedi | T331: AJ Pycroft | U331: Aleem Dar | V331: S Das | W331: C Shamshuddin | X331: Tapan Sharma | Y331: T20 | Z331: 20 | AA331: 6 | AB331: male | AC331: club | AD331: SR Watson, AM Rahane, R Dravid, STR Binny, BJ Hodge, KK Cooper, DH Yagnik, S Sreesanth, SK Trivedi, SW Tait, R Shukla | AE331: MS Bisla, G Gambhir, JH Kallis, MK Tiwary, EJG Morgan, YK Pathan, LR Shukla, R Bhatia, B Lee, Mohammed Shami, SP Narine
A332: Indian Premier League | B332: 2013 | C332: 9 | D332: 41373 | E332: Bangalore | F332: M Chinnaswamy Stadium | G332: Royal Challengers Bangalore | H332: Sunrisers Hyderabad | I332: Sunrisers Hyderabad | J332: bat | K332: 162 | L332: 3 | M332: 161 | N332: 6 | O332: Royal Challengers Bangalore | P332: complete | Q332: 0 | R332: 7 | S332: V Kohli | T332: DC Boon | U332: S Ravi | V332: SJA Taufel | W332: CK Nandan | X332: KN Ananthapadmanabhan | Y332: T20 | Z332: 20 | AA332: 6 | AB332: male | AC332: club | AD332: MA Agarwal, CH Gayle, V Kohli, AB de Villiers, MC Henriques, KB Arun Karthik, R Vinay Kumar, M Kartik, JD Unadkat, RP Singh, M Muralitharan | AE332: PA Reddy, PA Patel, KC Sangakkara, CL White, NLTC Perera, A Ashish Reddy, GH Vihari, BB Samantray, A Mishra, DW Steyn, I Sharma
A333: Indian Premier League | B333: 2013 | C333: 10 | D333: 41373 | E333: Mumbai | F333: Wankhede Stadium | G333: Mumbai Indians | H333: Delhi Daredevils | I333: Mumbai Indians | J333: bat | K333: 209 | L333: 5 | M333: 165 | N333: 9 | O333: Mumbai Indians | P333: complete | Q333: 44 | R333: 0 | S333: KD Karthik | T333: RS Madugalle | U333: M Erasmus | V333: VA Kulkarni | W333: S Asnani | X333: RM Deshpande | Y333: T20 | Z333: 20 | AA333: 6 | AB333: male | AC333: club | AD333: RT Ponting, SR Tendulkar, KD Karthik, RG Sharma, KA Pollard, AT Rayudu, Harbhajan Singh, R Dhawan, MG Johnson, PP Ojha, SL Malinga | AE333: UBT Chand, DA Warner, DPMD Jayawardene, MC Juneja, BMAJ Mendis, IK Pathan, KM Jadhav, S Nadeem, M Morkel, A Nehra, UT Yadav
A334: Indian Premier League | B334: 2013 | C334: 11 | D334: 41374 | E334: Chandigarh | F334: Punjab Cricket Association Stadium, Mohali | G334: Kings XI Punjab | H334: Chennai Super Kings | I334: Chennai Super Kings | J334: field | K334: 138 | L334: 10 | M334: 139 | N334: 0 | O334: Chennai Super Kings | P334: complete | Q334: 0 | R334: 10 | S334: MEK Hussey | T334: AJ Pycroft | U334: Aleem Dar | V334: C Shamshuddin | W334: S Das | X334: Nitin Menon | Y334: T20 | Z334: 20 | AA334: 6 | AB334: male | AC334: club | AD334: Mandeep Singh, AC Gilchrist, M Vohra, DJ Hussey, Gurkeerat Singh, Azhar Mahmood, R Sathish, PP Chawla, RJ Harris, P Kumar, P Awana | AE334: M Vijay, MEK Hussey, SK Raina, S Badrinath, MS Dhoni, RA Jadeja, DJ Bravo, R Ashwin, DP Nannes, CH Morris, AS Rajpoot
A335: Indian Premier League | B335: 2013 | C335: 12 | D335: 41375 | E335: Bangalore | F335: M Chinnaswamy Stadium | G335: Royal Challengers Bangalore | H335: Kolkata Knight Riders | I335: Royal Challengers Bangalore | J335: field | K335: 158 | L335: 2 | M335: 154 | N335: 8 | O335: Royal Challengers Bangalore | P335: complete | Q335: 0 | R335: 8 | S335: CH Gayle | T335: DC Boon | U335: Asad Rauf | V335: AK Chaudhary | W335: S Asnani | X335: KN Ananthapadmanabhan | Y335: T20 | Z335: 20 | AA335: 6 | AB335: male | AC335: club | AD335: CH Gayle, MA Agarwal, V Kohli, AB de Villiers, MC Henriques, KB Arun Karthik, KL Rahul, R Vinay Kumar, RP Singh, JD Unadkat, M Muralitharan | AE335: MS Bisla, G Gambhir, JH Kallis, YK Pathan, MK Tiwary, EJG Morgan, R Bhatia, R McLaren, PJ Sangwan, SP Narine, L Balaji
... A395: Indian Premier League | B395: 2013 | C395: 72 | D395: 41413 | E395: Hyderabad | F395: Rajiv Gandhi International Stadium, Uppal | G395: Sunrisers Hyderabad | H395: Kolkata Knight Riders | I395: Kolkata Knight Riders | J395: bat | K395: 132 | L395: 5 | M395: 130 | N395: 7 | O395: Sunrisers Hyderabad | P395: complete | Q395: 0 | R395: 5 | S395: PA Patel | T395: Raju Mukherjee | U395: Asad Rauf | V395: S Asnani | W395: AK Chaudhary | X395: A Nand Kishore | Y395: T20 | Z395: 20 | AA395: 6 | AB395: male | AC395: club | AD395: PA Patel, S Dhawan, GH Vihari, CL White, NLTC Perera, DJG Sammy, BB Samantray, KV Sharma, A Mishra, DW Steyn, Anand Rajan | AE395: MS Bisla, G Gambhir, JH Kallis, EJG Morgan, YK Pathan, RN ten Doeschate, P Dogra, SP Narine, Iqbal Abdulla, PJ Sangwan, Mohammed Shami
A396: Indian Premier League | B396: 2013 | C396: N/A | D396: 41415 | E396: Delhi | F396: Feroz Shah Kotla | G396: Chennai Super Kings | H396: Mumbai Indians | I396: Chennai Super Kings | J396: bat | K396: 192 | L396: 1 | M396: 144 | N396: 10 | O396: Chennai Super Kings | P396: complete | Q396: 48 | R396: 0 | S396: MEK Hussey | T396: RS Mahanama | U396: NJ Llong | V396: RJ Tucker | W396: S Ravi | X396: CK Nandan | Y396: T20 | Z396: 20 | AA396: 6 | AB396: male | AC396: club | AD396: MEK Hussey, M Vijay, SK Raina, MS Dhoni, RA Jadeja, S Badrinath, DJ Bravo, JA Morkel, CH Morris, R Ashwin, MM Sharma | AE396: DR Smith, AP Tare, KD Karthik, RG Sharma, KA Pollard, AT Rayudu, Harbhajan Singh, MG Johnson, SL Malinga, PP Ojha, MM Patel
A397: Indian Premier League | B397: 2013 | C397: N/A | D397: 41416 | E397: Delhi | F397: Feroz Shah Kotla | G397: Rajasthan Royals | H397: Sunrisers Hyderabad | I397: Sunrisers Hyderabad | J397: bat | K397: 135 | L397: 6 | M397: 132 | N397: 7 | O397: Rajasthan Royals | P397: complete | Q397: 0 | R397: 4 | S397: BJ Hodge | T397: RS Mahanama | U397: S Ravi | V397: RJ Tucker | W397: NJ Llong | X397: CK Nandan | Y397: T20 | Z397: 20 | AA397: 6 | AB397: male | AC397: club | AD397: R Dravid, AM Rahane, SR Watson, DH Yagnik, STR Binny, SV Samson, BJ Hodge, JP Faulkner, KK Cooper, VS Malik, SK Trivedi | AE397: PA Patel, S Dhawan, GH Vihari, CL White, DJG Sammy, NLTC Perera, BB Samantray, KV Sharma, DW Steyn, A Mishra, I Sharma
A398: Indian Premier League | B398: 2013 | C398: N/A | D398: 41418 | E398: Kolkata | F398: Eden Gardens | G398: Mumbai Indians | H398: Rajasthan Royals | I398: Rajasthan Royals | J398: bat | K398: 169 | L398: 6 | M398: 165 | N398: 6 | O398: Mumbai Indians | P398: complete | Q398: 0 | R398: 4 | S398: Harbhajan Singh | T398: RS Madugalle | U398: C Shamshuddin | V398: SJA Taufel | W398: HDPK Dharmasena | X398: K Srinath | Y398: T20 | Z398: 20 | AA398: 6 | AB398: male | AC398: club | AD398: DR Smith, AP Tare, KD Karthik, RG Sharma, KA Pollard, AT Rayudu, Harbhajan Singh, R Dhawan, MG Johnson, SL Malinga, PP Ojha | AE398: R Dravid, AM Rahane, SR Watson, SV Samson, STR Binny, BJ Hodge, KK Cooper, DH Yagnik, JP Faulkner, VS Malik, SK Trivedi
...

Sheet Aggregate functions
B5: Matches | C5: =COUNT(ipl_comprehensive_dataset!C2:C1244) -> 1169
B7: Total Runs | C7: =SUM(ipl_comprehensive_dataset!M:M,ipl_comprehensive_dataset!K:K) -> 401738 | E7: Team 1 | F7: =SUM(ipl_comprehensive_dataset!K:K) -> 206153
C8: =SUM(ipl_comprehensive_dataset!M1:M1244,ipl_comprehensive_dataset!K2:K1244) -> 401738 | E8: Team 2 | F8: =SUM(ipl_comprehensive_dataset!M:M) -> 195585 | H8: 12 | J8: count | K8: =COUNT(H8:H15) -> 3
H9: Surj
H10: 46419 | J10: counta | K10: =COUNTA(H8:H11,H12,H13,H14,H15) -> 6
H11: 20206
J12: countblank | K12: =COUNTBLANK(H8:H15) -> 2
B13: Region | C13: Sales (in Lakhs) | H13: =1/0 -> #DIV/0!
B14: North | C14: 23 | E14: sum | F14: =SUM(C14,C15,C16,C18,C19,C21,C22) -> 315 | K14: 2
B15: East | C15: 57 | E15: sum | F15: =SUM(C14:C22) -> 315 | H15: =1/0 -> #DIV/0!
B16: South | C16: 40 | E16: sum | F16: =SUM(C14,C16,C19,C22) -> 157
B17: West | C17: abc | E17: sum | F17: =SUM(C14:C16,C18:C19,C22) -> 243
B18: Central | C18: 29 | E18: avg | F18: =AVERAGE(C14:C22) -> 45 | J18: 1
B19: North-East | C19: 33 | E19: min | F19: =MIN(C14:C22) -> 23 | J19: 2
B20: South-West | E20: max | F20: =MAX(C14:C22) -> 72 | J20: 3
B21: South-Central | C21: 72 | E21: count | F21: =COUNT(C14:C22) -> 7 | J21: 3
B22: North-west | C22: 61 | E22: counta | F22: =COUNTA(C14:C22) -> 8 | J22: 4
E23: count blank | F23: =COUNTBLANK(C14:C22) -> 1 | H23: =COUNT(_xlfn.UNIQUE(J18:J22)) -> 4
E24: small | F24: =SMALL(C14:C22,2) -> 29
E25: large | F25: =LARGE(C14:C22,7) -> 23

Sheet IFs
B2: Emp Code | C2: Employee Name | D2: Address | E2: City | F2: Region | G2: Department | H2: Basic | J2: SUM | K2: =SUM(H3:H22) -> 184600 | L2: =_xlfn.FORMULATEXT(K2) -> =SUM(H3:H22) | M2: Q-1: Find total Salary Distributed.
B3: 7 | C3: Prakash Dutta | D3: Elgin Road | E3: Kolkata | F3: E | G3: Marketing | H3: 4500 | J3: AVERAGE | K3: =AVERAGE(H3:H22) -> 9230 | L3: =_xlfn.FORMULATEXT(K3) -> =AVERAGE(H3:H22) | M3: Q-2: Find Average Salary received by an employee
B4: 15 | C4: Prateek Babbar | D4: North Road | E4: Delhi | F4: N | G4: Marketing | H4: 4500 | J4: MAX | K4: =MAX(H3:H22) -> 16250 | L4: =_xlfn.FORMULATEXT(K4) -> =MAX(H3:H22) | M4: Q-3: Find MaximumSalary received by an employee
B5: 9 | C5: Arjun Jain | D5: MG Road | E5: Mumbai | F5: W | G5: Training | H5: 6250 | J5: MIN | K5: =MIN(H3:H22) -> 4500 | L5: =_xlfn.FORMULATEXT(K5) -> =MIN(H3:H22) | M5: Q-4: Find Minimum Salary received by an employee
B6: 17 | C6: Satish Puri | D6: Bandra | E6: Mumbai | F6: W | G6: Operation | H6: 6250 | J6: COUNT | K6: =COUNT(B3:B22) -> 20 | L6: =_xlfn.FORMULATEXT(K6) -> =COUNT(B3:B22) | M6: Q-5: Find total employees working
B7: 8 | C7: Manisha Guha | D7: Alipore | E7: Kolkata | F7: E | G7: R&D | H7: 6275 | J7: COUNTA | K7: =COUNTA(F3:F22) -> 20 | L7: =_xlfn.FORMULATEXT(K7) -> =COUNTA(F3:F22) | M7: Q-6: Find total regions
B8: 16 | C8: Sukanya Reddy | E8: Mangalore | F8: S | G8: R&D | H8: 6275 | J8: COUNtBLANK | K8: =COUNTBLANK(D3:D21) -> 3 | L8: =_xlfn.FORMULATEXT(K8) -> =COUNTBLANK(D3:D21) | M8: Q-7: Find number of missing sales
B9: 6 | C9: Jharna Biswal | D9: Link Road | E9: Cuttack | F9: E | G9: Accounts | H9: 6400 | J9: COUNTIF | K9: =COUNTIF(H3:H22,">10000") -> 7 | L9: =_xlfn.FORMULATEXT(K9) -> =COUNTIF(H3:H22,">10000") | M9: Q-8: Find count of salaries greater than 10k
B10: 14 | C10: Ashwini | D10: Sector 9 | E10: Mangalore | F10: S | G10: Accounts | H10: 6400 | J10: COUNTIF | K10: =COUNTIF(G3:G22,"=r&d") -> 5 | L10: =_xlfn.FORMULATEXT(K10) -> =COUNTIF(G3:G22,"=r&d") | M10: Q-9: Find number of employees working in R&D dept
B11: 10 | C11: Arjun Kapoor | E11: Bangalore | F11: S | G11: Accounts | H11: 8750 | J11: COUNTIF | K11: =COUNTIF(F3:F22,"=S") -> 7 | L11: =_xlfn.FORMULATEXT(K11) -> =COUNTIF(F3:F22,"=S") | M11: Q-10: Find number of employees from S Region
B12: 18 | C12: Anjum Chopra | D12: Worli | E12: Mumbai | F12: W | G12: R&D | H12: 8750 | J12: SUMIF | K12: =SUMIF(F3:F22,"=E",H3:H22) -> 17175 | L12: =_xlfn.FORMULATEXT(K12) -> =SUMIF(F3:F22,"=E",H3:H22) | M12: Q-11: Find total Salary distributed to E Region
B13: 1 | C13: JP Kumar | D13: Andheri (W) | E13: Mumbai | F13: W | G13: Training | H13: 10000 | J13: AVERAGEIF | K13: =AVERAGEIF(G3:G22,"Training",H3:H22) -> 11750 | L13: =_xlfn.FORMULATEXT(K13) -> =AVERAGEIF(G3:G22,"Training",H3:H22) | M13: Q-12: Find Average Salary received by Training Dept employees
B14: 12 | C14: Shahid Khan | D14: M.G Road | E14: Mangalore | F14: S | G14: R&D | H14: 10000 | J14: COUNTIF | K14: =COUNTIF(E3:E15,"Mumbai") -> 4 | L14: =_xlfn.FORMULATEXT(K14) -> =COUNTIF(E3:E15,"Mumbai") | M14: Q-13: Find count of employees from Mumbai City
B15: 20 | C15: Manish Grover | D15: L L R Road | E15: Noida | F15: N | G15: Training | H15: 10000
B16: 3 | C16: Priya Agarwal | D16: Sector 9 | F16: N | G16: Marketing | H16: 11250 | J16: SUMIFS | K16: =SUMIFS(H3:H22,G3:G22,"Training",F3:F22,"W") -> 16250 | L16: =_xlfn.FORMULATEXT(K16) -> =SUMIFS(H3:H22,G3:G22,"Training",F3:F22,"W") | M16: Q-1 Total Salary of Training Department Employees form W Region
B17: 11 | C17: Abrar | D17: Jayanagar | E17: Bangalore | F17: S | G17: Marketing | H17: 11250 | J17: AVERAGEIFS | K17: =AVERAGEIFS(H3:H22,G3:G22,"tRAINING",F3:F22,"w") -> 8125 | L17: =_xlfn.FORMULATEXT(K17) -> =AVERAGEIFS(H3:H22,G3:G22,"tRAINING",F3:F22,"w") | M17: Q-2 Average Salary of Training Department Employees form W Region
B18: 19 | C18: Akram Khan | D18: S P B Road | E18: Pune | F18: W | G18: Operation | H18: 11250 | J18: COUNTIFS | K18: =COUNTIFS(G3:G22,"training",F3:F22,"w") -> 2 | L18: =_xlfn.FORMULATEXT(K18) -> =COUNTIFS(G3:G22,"training",F3:F22,"w") | M18: Q-3 Total Number of Employees from Training Department and form W Region
B19: 2 | C19: Anjali Thakur | D19: Govindpuri | E19: Delhi | F19: N | G19: Accounts | H19: 12000 | J19: MAXIFS | K19: =_xlfn.MAXIFS(H3:H22,G3:G22,"training",F3:F22,"w") -> 10000 | L19: =_xlfn.FORMULATEXT(K19) -> =MAXIFS(H3:H22,G3:G22,"training",F3:F22,"w") | M19: Q-4 Max Salary of Employees from Training Department and form W Region
B20: 4 | C20: R Vasu | D20: Egmore | E20: Chennai | F20: S | G20: R&D | H20: 12000 | J20: MINIFS | K20: =_xlfn.MINIFS(H3:H22,G3:G22,G5,F3:F22,F5) -> 6250 | L20: =_xlfn.FORMULATEXT(K20) -> =MINIFS(H3:H22,G3:G22,G5,F3:F22,F5) | M20: Q-5 Min salary of Employees from Training Department and form W Region
B21: 5 | C21: Sanjay Gupta | E21: Delhi | F21: N | G21: Training | H21: 16250 | J21: SUMIFS | K21: =SUMIFS(H3:H22,G3:G22,G8,E3:E22,E8) -> 16275 | L21: =_xlfn.FORMULATEXT(K21) -> =SUMIFS(H3:H22,G3:G22,G8,E3:E22,E8) | M21: Q-6 Total Salary of R&D Department Employees from Manglore City
B22: 13 | C22: Anupam Mishra | D22: Govindpuri | E22: Mysore | F22: S | G22: Training | H22: 16250 | J22: COUNTIFS | K22: =COUNTIFS(H3:H22,">8000",H3:H22,"<12000") -> 8 | L22: =_xlfn.FORMULATEXT(K22) -> =COUNTIFS(H3:H22,">8000",H3:H22,"<12000") | M22: Q-7 Total Number of employees earning > 8000 and < 12000
M23: Q-7 Total Number of employees earning > 8000 and < 12000
J24: RANK
J25: RANK
I26: 2nd largest | J26: LARGE | K26: =LARGE(H3:H22,2) -> 16250 | L26: =_xlfn.FORMULATEXT(K26) -> =LARGE(H3:H22,2) | M26: using unique | N26: =LARGE(_xlfn.UNIQUE(H3:H22),2) -> 12000 | O26: =_xlfn.FORMULATEXT(N26) -> =LARGE(UNIQUE(H3:H22),2)
C27: 100 | D27: $100 | I27: 3rd smallest | J27: SMALL | K27: =SMALL(H3:H22,3) -> 6250 | L27: =_xlfn.FORMULATEXT(K27) -> =SMALL(H3:H22,3) | M27: using unique | N27: =SMALL(_xlfn.UNIQUE(H3:H22),3) -> 6275 | O27: =_xlfn.FORMULATEXT(N27) -> =SMALL(UNIQUE(H3:H22),3)
C28: 200 | D28: $200
C29: =SUM(C28,C27) -> 300 | D29: =SUM(D27,D28) -> 0
